Workbook

Sheet FRONT 
A1: BRANCH : | H1: RIDER DELIVERY SUMMARY
A2: DATE : | B2: 46287 | E2: SYSTEM DATE: | F2: 46287 | H2: RIDER NAME (1-4) | I2: PRODUCT AMOUNT | J2: DEL FEE | K2: SUBTOTAL | L2: INCENTIVES | M2: TOTAL | N2: REMARKS
H3: JAIME | I3: =DELIVERY!D29+DELIVERY!L29 -> 4650 | J3: =DELIVERY!E29+DELIVERY!M29 -> 137 | K3: =I3+J3 -> 4787 | M3: =K3-L3 -> 4787
A4: SALES Breakdown (CASH) | E4: Number of products | H4: NAME | I4: =DELIVERY!D59+DELIVERY!L59 -> 0 | J4: =DELIVERY!E59+DELIVERY!M59 -> 0 | K4: =I4+J4 -> 0 | M4: =K4-L4 -> 0
B5: Walk in | C5: ='WALK IN'!D30 -> 3375 | E5: Walk-in: | F5: ='WALK IN'!C30+'WALK IN'!I30 -> 8 | I5: 0 | J5: 0 | K5: =I5+J5 -> 0 | M5: =K5-L5 -> 0
B6: Delivery | C6: =DELIVERY!D29+DELIVERY!D59+DELIVERY!D93+DELIVERY!D126 -> 0 | E6: Delivery: | F6: =DELIVERY!C29+DELIVERY!K29+DELIVERY!C59+DELIVERY!K59 -> 4 | I6: 0 | J6: 0 | K6: =I6+J6 -> 0 | M6: =K6-L6 -> 0
B7: Franchise | C7: ='WALK IN'!D55 -> 0 | E7: Franchise: | F7: ='WALK IN'!C55+'WALK IN'!I55+DELIVERY!C93+DELIVERY!K93+SHIPPING!C46 -> 0
B8: Prothin Dealer | C8: ='WALK IN'!D83 -> 0 | E8: Prothin Dealers: | F8: ='WALK IN'!C83+'WALK IN'!I83+DELIVERY!C126+DELIVERY!K126+SHIPPING!K46 -> 0
B9: Agent (Cash) | C9: ='WALK IN'!D111+DELIVERY!D159 -> 0 | E9: Shipping: | F9: =SHIPPING!C19+SHIPPING!K19 -> 0 | H9: Total: | I9: =I3+I4+I5+I6 -> 4650 | J9: =J3+J4+J5+J6 -> 137 | K9: =K3+K4+K5+K6 -> 4787 | L9: =SUM(L3:L8) -> 0 | M9: =SUM(M3:M8) -> 4787
B10: Delivery Fee | C10: =DELIVERY!E29+DELIVERY!E59+DELIVERY!E159 -> 0 | E10: Apparels: | F10: 0
B11: SUBTOTAL | C11: =C5+C6++C7+C8+C10 -> 3375 | E11: Equipment: | F11: 0 | H11: MONEY BREAKDOWN | J11: Quantity | L11: EXPENSES
E12: Agent: | F12: ='WALK IN'!C111+'WALK IN'!I111+DELIVERY!C159+DELIVERY!K159+SHIPPING!C74 -> 0 | H12: 1000 | I12: X | L12: NAME | M12: PARTICULAR/S | N12: AMOUNT
B13: Credit Card (Walk In) | C13: ='CREDIT CARD'!E21 -> 0 | H13: 500 | I13: X | L13: Rent
B14: Credit Card (Delivery) | C14: ='CREDIT CARD'!E74+'CREDIT CARD'!E99+'CREDIT CARD'!E124 -> 0 | H14: 200 | I14: X | L14: Meralco
B15: Credit Card (Agent) | C15: ='CREDIT CARD'!E49 -> 0 | H15: 100 | I15: X | L15: Internet (Globe or Royal cab)
B16: Walk in (Online) | C16: ='WALK IN'!J30 -> 2300 | E16: Delivery Fee (Online) | F16: =DELIVERY!E29+DELIVERY!M29+DELIVERY!E93+DELIVERY!M93+DELIVERY!E126+DELIVERY!M126 -> 137 | H16: 50 | I16: X | L16: Water Bills
B17: Walk in (Online) - Franchise | C17: ='WALK IN'!$J$55 -> 0 | E17: Delivery Fee (Credit Card) | F17: ='CREDIT CARD'!F21 -> 0 | H17: 20 | I17: X | L17: INCENTIVES ETC. | N17: 200
B18: Walk in (Online) - Prothin Dealer | C18: ='WALK IN'!$J$83 -> 0 | E18: Franchise (Online) | H18: 10 | I18: X | L18: Load for Store CP
B19: Walk in (Online) - Agent | C19: ='WALK IN'!J111 -> 0 | E19: Prothin Dealer (Online) | F19: =DELIVERY!$L$126 -> 0 | H19: 5 | I19: X | L19: ABONO LALAMOVE | N19: 137
B20: Delivery (Online) | C20: =DELIVERY!$L$29 -> 4650 | E20: Shipping Fee | F20: =SHIPPING!E19+SHIPPING!E46+SHIPPING!M46 -> 0 | H20: 1 | I20: X
B21: Delivery (Online) - Franchise | C21: =DELIVERY!$L$93 -> 0 | E21: Agent (Online) | F21: =DELIVERY!E159+DELIVERY!M159+SHIPPING!E74 -> 0
B22: Delivery (Online) Prothin Dealer | C22: =DELIVERY!$L$126 -> 0 | E22: TOTAL | F22: =SUM(F16:F21) -> 137
B23: Delivery (Online) Agent | C23: =DELIVERY!L159 -> 0 | H23: check payment
B24: Shipping (LBC/LALAMOVE) | C24: =SHIPPING!D19 -> 0 | H24: TOTAL | K24: =SUM(K12:K23) -> 0 | N24: =SUM(N13:N23) -> 337
B25: Shipping - Franchise | C25: =SHIPPING!D46 -> 0
B26: Shipping - Prothin Dealer | C26: =SHIPPING!L46 -> 0
B27: Shipping - Agent | C27: =SHIPPING!D74 -> 0
B28: Shipping (Shopee/Lazada) | C28: =SHIPPING!M19 -> 0 | L28: OTHERS:
B29: TOTAL ONLINE, CC & SHIPPING | C29: =SUM(C13:C28) -> 6950 | H29: RIDER/DRIVER EXPENSE | L29: lalamove to warehouse
H30: NAME : | I30: PARTICULAR/S | J30: AMOUNT | L30: creditcard terminal
B31: TOTAL WALK IN : | D31: =C5+C13+C16 -> 5675
B32: (CASH,CC, AND ONLINE)
B33: TOTAL DELIVERY : | D33: =C6+C14+C20 -> 4650
B34: (CASH,CC, AND ONLINE)
B35: TOTAL SHIPPING : | D35: =C24+C28 -> 0
B36: (CASH,CC, AND ONLINE)
B37: TOTAL FRANCHISE : | D37: =C7+C25+C17+C21 -> 0 | L37: TOTAL OTHER EXP: | N37: =SUM(N29:N36) -> 0
B38: (CASH AND ONLINE)
B39: TOTAL PROTHIN DEALER : | D39: =C8+C22+C26+C18 -> 0
B40: (CASH AND ONLINE)
B41: TOTAL AGENT : | D41: =C9+C15+C19+C23+C27 -> 0
B42: (CASH,ONLINE AND CC) | H42: TOTAL RIDER/DRIVER EXPENSE | J42: =SUM(J31:J40) -> 0
A43: EXPENSES | E43: NOTES: | F43: FREEBIES
B44: Riders/Drivers (Incentive) | C44: ………………... | D44: =L9 -> 0 | F44: prothin stainless shaker | H44: SHIPPING EXPENSE | J44: ORDERS | K44: MARKETING
B45: Riders/Drivers (Expense) | C45: ………………... | D45: =J42 -> 0 | F45: gws lettering shaker | G45: 1 | H45: NAME | I45: PARTICULAR/S | J45: AMOUNT | K45: AMOUNT
B46: Shipping Expense (TOTAL) | C46: ………………... | D46: =J56+K56 -> 0 | F46: gws plain text | G46: 1
B47: MAJOR EXPENSES | C47: ………………... | D47: =N24 -> 337
B48: OTHER EXPENSES | C48: ………………... | D48: =N37 -> 0
B49: TOTAL | C49: ………………... | D49: =SUM(D44:D48) -> 337
A51: SUMMARY (for bank deposit)
B52: CASH | C52: =C11 -> 3375
A53: less | B53: EXPENSES | C53: =D49 -> 337 | IW53: 9
B54: TOTAL | C54: =C52-C53 -> 3038
A56: TOTAL CASH DEPOSIT: | C56: =C54 -> 3038 | D56: =C54-C56 -> 0 | H56: TOTAL RIDER/DRIVER EXPENSE | J56: =SUM(J46:J55) -> 0 | K56: =SUM(K46:K55) -> 0
A57: OVERALL SALES: | C57: =C11+C29-D49 -> 9988
A58: TOTAL PRODUCTS (WALK IN) | C58: =F5 -> 8
A59: TOTAL PRODUCTS (DELIVERY) | C59: =F6 -> 4
A60: TOTAL PRODUCTS (SHIPPING) | C60: =F9 -> 0
A61: TOTAL APPARELS: | C61: =F10 -> 0
A62: TOTAL EQUIPMENT: | C62: =F11 -> 0 | E62: PREPARED BY :
A63: TOTAL FRANCHISE | C63: =F7 -> 0 | E63: regina latagan | F63: 46287
A64: TOTAL PROTHIN DEALER | C64: =F8 -> 0 | E64: Name and Signature/Date
A65: TOTAL AGENT | C65: =F12 -> 0

Sheet WALK IN
A1: WALK IN (CASH) | G1: WALK IN (ONLINE)
A2: DAILY PRODUCT | G2: DAILY PRODUCT
A3: DATE: | B3: 46287 | G3: DATE: | H3: 46287
A4: BRANCH: | B4: Dasma Branch | G4: BRANCH: | H4: Dasma Branch
A5: DR#/ SI # | B5: ITEMS | C5: QTY | D5: AMOUNT | E5: REMARKS | G5: DR#/ SI # | H5: ITEMS | I5: QTY | J5: AMOUNT | K5: REMARKS
A6: 15246 | B6: Prothin Whey Isolate 60s | C6: 1 | D6: 3000 | G6: 15248 | H6: Muscle Tech Mass Extreme 6lbs | I6: 1 | J6: 2100
B7: Gws plain Text | C7: 1 | D7: 0 | H7: Promatrix Shaker | I7: 1 | J7: 200
B8: Plastic L | C8: 1 | D8: 0 | H8: Plastic L | I8: 1 | J8: 0
A9: 15247 | B9: HYDR 8 15 Serving | C9: 1 | D9: 375
B10: Plastic M | C10: 1 | D10: 0
B30: TOTAL | C30: =SUM(C6:C29) -> 5 | D30: =SUM(D6:D29) -> 3375 | H30: TOTAL | I30: =SUM(I6:I29) -> 3 | J30: =SUM(J6:J29) -> 2300
A33: WALK IN (FRANCHISE CASH) | G33: WALK IN (FRANCHISE ONLINE)
A34: DAILY PRODUCT | G34: DAILY PRODUCT
A35: DATE: | G35: DATE:
A36: BRANCH: | G36: BRANCH:
A37: DR#/ SI # | B37: ITEMS | C37: QTY | D37: AMOUNT | E37: REMARKS | G37: DR#/ SI # | H37: ITEMS | I37: QTY | J37: AMOUNT | K37: REMARKS
B55: TOTAL | C55: =SUM(C38:C54) -> 0 | D55: =SUM(D38:D54) -> 0 | H55: TOTAL | I55: =SUM(I38:I54) -> 0 | J55: =SUM(J38:J54) -> 0
A58: WALK IN (PROTHIN DEALER CASH) | G58: WALK IN (PROTHIN ONLINE)
A59: DAILY PRODUCT | G59: DAILY PRODUCT
A60: DATE: | B60: 46271 | G60: DATE: | H60: 46271
A61: BRANCH: | B61: Dasma Branch | G61: BRANCH: | H61: Dasma Branch
A62: DR#/ SI # | B62: ITEMS | C62: QTY | D62: AMOUNT | E62: REMARKS | G62: DR#/ SI # | H62: ITEMS | I62: QTY | J62: AMOUNT | K62: REMARKS
B83: TOTAL | C83: =SUM(C63:C82) -> 0 | D83: =SUM(D63:D82) -> 0 | H83: TOTAL | I83: =SUM(I63:I82) -> 0 | J83: =SUM(J63:J82) -> 0
A86: WALK IN ( AGENT CASH ) | G86: WALK IN (AGENT ONLINE)
A87: DAILY PRODUCT | G87: DAILY PRODUCT
A88: DATE: | B88: 46286 | G88: DATE: | H88: 46287
A89: BRANCH: | B89: Dasma Branch | G89: BRANCH: | H89: Dasma Branch
A90: DR#/ SI # | B90: ITEMS | C90: QTY | D90: AMOUNT | E90: REMARKS | G90: DR#/ SI # | H90: ITEMS | I90: QTY | J90: AMOUNT | K90: REMARKS
B111: TOTAL | C111: =SUM(C91:C110) -> 0 | D111: =SUM(D91:D110) -> 0 | H111: TOTAL | I111: =SUM(I91:I110) -> 0 | J111: =SUM(J91:J110) -> 0

Sheet DELIVERY
A1: DELIVERY (CASH) | I1: DELIVERY (ONLINE)
A2: DAILY PRODUCT | I2: DAILY PRODUCT
A3: RIDER 1: | F3: DATE: | G3: 46271 | I3: RIDER 1: | N3: DATE: | O3: 46287
A4: BRANCH | B4: DASMA BRANCH | I4: BRANCH | J4: DASMA BRANCH
A5: DR#/ SI # | B5: ITEMS | C5: QTY | D5: AMOUNT | E5: DEL FEE | F5: TOTAL AMOUNT | G5: REMARKS | I5: DR#/ SI # | J5: ITEMS | K5: QTY | L5: AMOUNT | M5: DEL FEE | N5: TOTAL AMOUNT | O5: REMARKS
I6: 15245 | J6: Prothin Whey Isolate 60s | K6: 1 | L6: 3000 | M6: 137 | N6: 3000
J7: C4 Ripped 30s | K7: 1 | L7: 1650 | N7: 1650
J8: Gws Lettering Shaker | K8: 1 | L8: 0 | N8: 0
J9: Plastic XL | K9: 1 | L9: 0 | N9: 0
B29: TOTAL | C29: =SUM(C6:C28) -> 0 | D29: =SUM(D6:D28) -> 0 | E29: =SUM(E6:E28) -> 0 | F29: =SUM(F6:F28) -> 0 | J29: TOTAL | K29: =SUM(K6:K28) -> 4 | L29: =SUM(L6:L28) -> 4650 | M29: =SUM(M6:M28) -> 137 | N29: =SUM(N6:N28) -> 4650
A31: DELIVERY (CASH) | I31: DELIVERY (ONLINE)
A32: DAILY PRODUCT | I32: DAILY PRODUCT
A33: RIDER 2: | F33: DATE: | I33: RIDER 2: | N33: DATE:
A34: BRANCH | I34: BRANCH
A35: DR#/ SI # | B35: ITEMS | C35: QTY | D35: AMOUNT | E35: DEL FEE | F35: TOTAL AMOUNT | G35: REMARKS | I35: DR#/ SI # | J35: ITEMS | K35: QTY | L35: AMOUNT | M35: DEL FEE | N35: TOTAL AMOUNT | O35: REMARKS
B59: TOTAL | C59: =SUM(C36:C58) -> 0 | D59: =SUM(D36:D58) -> 0 | E59: =SUM(E36:E58) -> 0 | F59: =SUM(F36:F58) -> 0 | J59: TOTAL | K59: =SUM(K36:K58) -> 0 | L59: =SUM(L36:L58) -> 0 | M59: =SUM(M36:M58) -> 0 | N59: =SUM(N36:N58) -> 0
A64: DELIVERY (FRANCHISE CASH) | I64: DELIVERY (FRANCHISE ONLINE)
A65: DAILY PRODUCT | I65: DAILY PRODUCT
A66: DATE: | I66: DATE:
A67: BRANCH | I67: BRANCH
A68: DR#/ SI # | B68: ITEMS | C68: QTY | D68: AMOUNT | E68: DEL FEE | F68: TOTAL AMOUNT | G68: REMARKS | I68: DR#/ SI # | J68: ITEMS | K68: QTY | L68: AMOUNT | M68: DEL FEE | N68: TOTAL AMOUNT | O68: REMARKS
C93: =SUM(C69:C92) -> 0 | D93: =SUM(D69:D92) -> 0 | E93: =SUM(E69:E92) -> 0 | F93: =SUM(F69:F92) -> 0 | K93: =SUM(K69:K92) -> 0 | L93: =SUM(L69:L92) -> 0 | M93: =SUM(M69:M92) -> 0 | N93: =SUM(N69:N92) -> 0
A96: DELIVERY (PROTHIN DEALER CASH) | I96: DELIVERY (PROTHIN DEALER ONLINE)
A97: DAILY PRODUCT | I97: DAILY PRODUCT
A98: DATE: | B98: SEPT, 5 ,2026 | I98: DATE: | J98: 46270
A99: BRANCH | B99: DASMA BRANCH | I99: BRANCH | J99: DASSMA BRANCH
A100: DR#/ SI # | B100: ITEMS | C100: QTY | D100: AMOUNT | E100: DEL FEE | F100: TOTAL AMOUNT | G100: REMARKS | I100: DR#/ SI # | J100: ITEMS | K100: QTY | L100: AMOUNT | M100: DEL FEE | N100: TOTAL AMOUNT | O100: REMARKS
C126: =SUM(C101:C125) -> 0 | D126: =SUM(D101:D125) -> 0 | E126: =SUM(E101:E125) -> 0 | F126: =SUM(F101:F125) -> 0 | K126: =SUM(K101:K125) -> 0 | L126: =SUM(L101:L125) -> 0 | M126: =SUM(M101:M125) -> 0 | N126: =SUM(N101:N125) -> 0
A129: DELIVERY (AGENT CASH) | I129: DELIVERY (AGENT ONLINE)
A130: DAILY PRODUCT | I130: DAILY PRODUCT
A131: DATE: | B131: September 5,2026 | I131: DATE: | J131: September 5 ,2026
A132: BRANCH | B132: DASMA BRANCH | I132: BRANCH | J132: DASMA BRANCH
A133: DR#/ SI # | B133: ITEMS | C133: QTY | D133: AMOUNT | E133: DEL FEE | F133: TOTAL AMOUNT | G133: REMARKS | I133: DR#/ SI # | J133: ITEMS | K133: QTY | L133: AMOUNT | M133: DEL FEE | N133: TOTAL AMOUNT | O133: REMARKS
C159: =SUM(C134:C158) -> 0 | D159: =SUM(D134:D158) -> 0 | E159: =SUM(E134:E158) -> 0 | F159: =SUM(F134:F158) -> 0 | K159: =SUM(K134:K158) -> 0 | L159: =SUM(L134:L158) -> 0 | M159: =SUM(M134:M158) -> 0 | N159: =SUM(N134:N158) -> 0

Sheet SHIPPING
A1: SHIPPING | I1: SHIPPING
A2: (LBC/LALAMOVE) | I2: (SHOPEE/LAZADA)
A3: DATE: | I3: DATE:
A4: BRANCH: | I4: BRANCH:
A5: DR/SI # | B5: ITEMS | C5: QTY | D5: AMOUNT | E5: SF | F5: TOTAL | G5: SHIP EXP | I5: DR/SI # | J5: ITEMS | K5: QTY | L5: AMOUNT | M5: OR INC | N5: CHARGES
C19: =SUM(C6:C18) -> 0 | D19: =SUM(D6:D18) -> 0 | E19: =SUM(E6:E18) -> 0 | G19: =SUM(G6:G18) -> 0 | K19: =SUM(K6:K18) -> 0 | L19: =SUM(L6:L18) -> 0 | M19: =SUM(M6:M18) -> 0 | N19: =SUM(N6:O18) -> 0
A21: SHIPPING | I21: SHIPPING
A22: ( FRANCHISE ) | I22: ( PROTHIN DEALER )
A23: DATE: | I23: DATE:
A24: BRANCH: | I24: BRANCH:
A25: DR/SI # | B25: ITEMS | C25: QTY | D25: AMOUNT | E25: SF | F25: TOTAL | G25: SHIP EXP | I25: DR/SI # | J25: ITEMS | K25: QTY | L25: AMOUNT | M25: SF | N25: TOTAL | O25: SHIP EXP
C46: =SUM(C26:C45) -> 0 | D46: =SUM(D26:D45) -> 0 | E46: =SUM(E26:E45) -> 0 | F46: =SUM(F26:F45) -> 0 | G46: =SUM(G26:G45) -> 0 | K46: =SUM(K26:K45) -> 0 | L46: =SUM(L26:L45) -> 0 | M46: =SUM(M26:M45) -> 0 | N46: =SUM(N26:N45) -> 0 | O46: =SUM(O26:O45) -> 0
A49: SHIPPING
A50: ( AGENT)
A51: DATE:
A52: BRANCH:
A53: DR/SI # | B53: ITEMS | C53: QTY | D53: AMOUNT | E53: SF | F53: TOTAL | G53: SHIP EXP
C74: =SUM(C54:C73) -> 0 | D74: =SUM(D54:D73) -> 0 | E74: =SUM(E54:E73) -> 0 | F74: =SUM(F54:F73) -> 0 | G74: =SUM(G54:G73) -> 0

Sheet CREDIT CARD
A1: CREDIT CARD REPORT (WALK-IN)
A2: DR#/SI# | B2: CUSTOMER NAME | C2: ITEM PURCHASED | D2: QTY | E2: AMOUNT | F2: DEL FEE | G2: TOTAL | H2: MID # | I2: SLIP # | J2: APR CODE | K2: BATCH #
G4: 0
G5: =SUM(E5+F5) -> 0
G8: =SUM(E8+F8) -> 0
G9: =SUM(E9+F9) -> 0
G10: =SUM(E10+F10) -> 0
G11: =SUM(E11+F11) -> 0
G12: =SUM(E12+F12) -> 0
G13: =SUM(E13+F13) -> 0
G14: =SUM(E14+F14) -> 0
G15: =SUM(E15+F15) -> 0
G16: =SUM(E16+F16) -> 0
G17: =SUM(E17+F17) -> 0
G18: =SUM(E18+F18) -> 0
... G20: =SUM(E20+F20) -> 0
D21: =SUM(D3:D20) -> 0 | E21: =SUM(E3:E20) -> 0 | F21: =SUM(F3:F20) -> 0 | G21: =SUM(G3:G20) -> 0
A26: CREDIT CARD REPORT ( AGENT )
A27: DR# | B27: CUSTOMER NAME | C27: ITEM PURCHASED | D27: QTY | E27: AMOUNT | F27: DEL FEE | G27: TOTAL | H27: MID # | I27: SLIP # | J27: APR CODE | K27: BATCH #
G28: =SUM(E28+F28) -> 0
G29: =SUM(E29+F29) -> 0
G30: =SUM(E30+F30) -> 0
G31: =SUM(E31+F31) -> 0
G32: =SUM(E32+F32) -> 0
G33: =SUM(E33+F33) -> 0
G34: =SUM(E34+F34) -> 0
G35: =SUM(E35+F35) -> 0
G36: =SUM(E36+F36) -> 0
G37: =SUM(E37+F37) -> 0
G38: =SUM(E38+F38) -> 0
G39: =SUM(E39+F39) -> 0
... G48: =SUM(E48+F48) -> 0
D49: =SUM(D28:D48) -> 0 | E49: =SUM(E28:E48) -> 0 | F49: =SUM(F28:F48) -> 0 | G49: =SUM(G28:G48) -> 0
A51: CREDIT CARD REPORT (DELIVERY RIDER 1 )
A52: DR# | B52: CUSTOMER NAME | C52: ITEM PURCHASED | D52: QTY | E52: AMOUNT | F52: DEL FEE | G52: TOTAL | H52: MID # | I52: SLIP # | J52: APR CODE | K52: BATCH #
G53: =SUM(E53+F53) -> 0
G54: =SUM(E54+F54) -> 0
G55: =SUM(E55+F55) -> 0
G56: =SUM(E56+F56) -> 0
G57: =SUM(E57+F57) -> 0
G58: =SUM(E58+F58) -> 0
G59: =SUM(E59+F59) -> 0
G60: =SUM(E60+F60) -> 0
G61: =SUM(E61+F61) -> 0
G62: =SUM(E62+F62) -> 0
G63: =SUM(E63+F63) -> 0
G64: =SUM(E64+F64) -> 0
... G73: =SUM(E73+F73) -> 0
D74: =SUM(D53:D73) -> 0 | E74: =SUM(E53:E73) -> 0 | F74: =SUM(F53:F73) -> 0 | G74: =SUM(G53:G73) -> 0
A76: CREDIT CARD REPORT (DELIVERY RIDER 2)
A77: DR# | B77: CUSTOMER NAME | C77: ITEM PURCHASED | D77: QTY | E77: AMOUNT | F77: DEL FEE | G77: TOTAL | H77: MID # | I77: SLIP # | J77: APR CODE | K77: BATCH #
G78: =SUM(E78+F78) -> 0
G79: =SUM(E79+F79) -> 0
G80: =SUM(E80+F80) -> 0
G81: =SUM(E81+F81) -> 0
G82: =SUM(E82+F82) -> 0
G83: =SUM(E83+F83) -> 0
G84: =SUM(E84+F84) -> 0
G85: =SUM(E85+F85) -> 0
G86: =SUM(E86+F86) -> 0
G87: =SUM(E87+F87) -> 0
G88: =SUM(E88+F88) -> 0
G89: =SUM(E89+F89) -> 0
... G98: =SUM(E98+F98) -> 0
D99: =SUM(D78:D98) -> 0 | E99: =SUM(E78:E98) -> 0 | F99: =SUM(F78:F98) -> 0 | G99: =SUM(G78:G98) -> 0
A101: CREDIT CARD REPORT (DELIVERY RIDER 3)
A102: DR# | B102: CUSTOMER NAME | C102: ITEM PURCHASED | D102: QTY | E102: AMOUNT | F102: DEL FEE | G102: TOTAL | H102: MID # | I102: SLIP # | J102: APR CODE | K102: BATCH #
G103: =SUM(E103+F103) -> 0
G104: =SUM(E104+F104) -> 0
G105: =SUM(E105+F105) -> 0
G106: =SUM(E106+F106) -> 0
G107: =SUM(E107+F107) -> 0
G108: =SUM(E108+F108) -> 0
G109: =SUM(E109+F109) -> 0
G110: =SUM(E110+F110) -> 0
G111: =SUM(E111+F111) -> 0
G112: =SUM(E112+F112) -> 0
G113: =SUM(E113+F113) -> 0
G114: =SUM(E114+F114) -> 0
... G123: =SUM(E123+F123) -> 0
D124: =SUM(D103:D123) -> 0 | E124: =SUM(E103:E123) -> 0 | F124: =SUM(F103:F123) -> 0 | G124: =SUM(G103:G123) -> 0

Sheet RECEIPT TRACKER
A1: RECEIPT TRACKER | I1: Mode of Payment | Q1: .
A2: (MUST PRESENT ALL ORIGINAL YELLOW COPIES) | I2: CASH
A3: *ERASURES IN DR NOT ALLOWED* | I3: AR / PDC
A4: BRANCH: | B4: Dasma Branch | F4: DATE: | G4: 46287 | I4: ONLINE
A5: DR#/ SI # | B5: ITEMS | C5: QTY | D5: AMOUNT | E5: DF | F5: TOTAL | G5: TRANSACTION TYPE | I5: CREDIT CARD
A6: 15245 | B6: Prothin Whey Isolate 60s | C6: 1 | D6: 3000 | E6: 137 | F6: 3000 | G6: ONLINE | I6: CASH AGENT
B7: C4 Ripped 30s | C7: 1 | D7: 1650 | F7: 1650 | I7: AR / PDC AGENT
B8: Gws Lettering Shaker | C8: 1 | D8: 0 | F8: 0 | I8: ONLINE AGENT
B9: Plastic XL | C9: 1 | D9: 0 | F9: 0 | I9: CR. CARD AGENT
A10: 15246 | B10: Prothin Whey Isolate 60s | C10: 1 | D10: 3000 | F10: 3000 | G10: CASH
B11: Gws plain Text | C11: 1 | D11: 0 | F11: 0
B12: Plastic L | C12: 1 | D12: 0 | F12: 0
A13: 15247 | B13: HYDR 8 15 Serving | C13: 1 | D13: 375 | F13: 375 | G13: CASH
B14: Plastic M | C14: 1 | D14: 0 | F14: 0 | DH14: 4050 | DI14: 2594 | DJ14: PWR 60's Choco / Free PT Short (3pcs) | DK14: 3 | DL14: 4050 | DM14: 2594 | DN14: PWR 60's Choco / Free PT Short (3pcs) | DO14: 3 | DP14: 4050 | DQ14: 2594 | DR14: PWR 60's Choco / Free PT Short (3pcs) | DS14: 3 | DT14: 4050 | DU14: 2594 | DV14: PWR 60's Choco / Free PT Short (3pcs) | DW14: 3 | DX14: 4050 | DY14: 2594 | DZ14: PWR 60's Choco / Free PT Short (3pcs) | EA14: 3 | EB14: 4050 | EC14: 2594 | ED14: PWR 60's Choco / Free PT Short (3pcs) | EE14: 3 | EF14: 4050 | EG14: 2594 | EH14: PWR 60's Choco / Free PT Short (3pcs) | EI14: 3 | EJ14: 4050 | EK14: 2594 | EL14: PWR 60's Choco / Free PT Short (3pcs) | EM14: 3 | EN14: 4050 | EO14: 2594 | EP14: PWR 60's Choco / Free PT Short (3pcs) | EQ14: 3 | ER14: 4050 | ES14: 2594 | ET14: PWR 60's Choco / Free PT Short (3pcs) | EU14: 3 | EV14: 4050 | EW14: 2594 | EX14: PWR 60's Choco / Free PT Short (3pcs) | EY14: 3 | EZ14: 4050 | FA14: 2594 | FB14: PWR 60's Choco / Free PT Short (3pcs) | FC14: 3 | FD14: 4050 | FE14: 2594 | FF14: PWR 60's Choco / Free PT Short (3pcs) | FG14: 3 | FH14: 4050 | FI14: 2594 | FJ14: PWR 60's Choco / Free PT Short (3pcs) | FK14: 3 | FL14: 4050 | FM14: 2594 | FN14: PWR 60's Choco / Free PT Short (3pcs) | FO14: 3 | FP14: 4050 | FQ14: 2594 | FR14: PWR 60's Choco / Free PT Short (3pcs) | FS14: 3 | FT14: 4050 | FU14: 2594 | FV14: PWR 60's Choco / Free PT Short (3pcs) | FW14: 3 | FX14: 4050 | FY14: 2594 | FZ14: PWR 60's Choco / Free PT Short (3pcs) | GA14: 3 | GB14: 4050 | GC14: 2594 | GD14: PWR 60's Choco / Free PT Short (3pcs) | GE14: 3 | GF14: 4050 | GG14: 2594 | GH14: PWR 60's Choco / Free PT Short (3pcs) | GI14: 3 | GJ14: 4050 | GK14: 2594 | GL14: PWR 60's Choco / Free PT Short (3pcs) | GM14: 3 | GN14: 4050 | GO14: 2594 | GP14: PWR 60's Choco / Free PT Short (3pcs) | GQ14: 3 | GR14: 4050 | GS14: 2594 | GT14: PWR 60's Choco / Free PT Short (3pcs) | GU14: 3 | GV14: 4050 | GW14: 2594 | GX14: PWR 60's Choco / Free PT Short (3pcs) | GY14: 3 | GZ14: 4050 | HA14: 2594 | HB14: PWR 60's Choco / Free PT Short (3pcs) | HC14: 3 | HD14: 4050 | HE14: 2594 | HF14: PWR 60's Choco / Free PT Short (3pcs) | HG14: 3 | HH14: 4050 | HI14: 2594 | HJ14: PWR 60's Choco / Free PT Short (3pcs) | HK14: 3 | HL14: 4050 | HM14: 2594 | HN14: PWR 60's Choco / Free PT Short (3pcs) | HO14: 3 | HP14: 4050 | HQ14: 2594 | HR14: PWR 60's Choco / Free PT Short (3pcs) | HS14: 3 | HT14: 4050 | HU14: 2594 | HV14: PWR 60's Choco / Free PT Short (3pcs) | HW14: 3 | HX14: 4050 | HY14: 2594 | HZ14: PWR 60's Choco / Free PT Short (3pcs) | IA14: 3 | IB14: 4050 | IC14: 2594 | ID14: PWR 60's Choco / Free PT Short (3pcs) | IE14: 3 | IF14: 4050 | IG14: 2594 | IH14: PWR 60's Choco / Free PT Short (3pcs) | II14: 3 | IJ14: 4050 | IK14: 2594 | IL14: PWR 60's Choco / Free PT Short (3pcs) | IM14: 3 | IN14: 4050 | IO14: 2594 | IP14: PWR 60's Choco / Free PT Short (3pcs) | IQ14: 3 | IR14: 4050 | IS14: 2594 | IT14: PWR 60's Choco / Free PT Short (3pcs) | IU14: 3 | IV14: 4050 | IW14: 2594 | IX14: PWR 60's Choco / Free PT Short (3pcs) | IY14: 3 | IZ14: 4050 | JA14: 2594 | JB14: PWR 60's Choco / Free PT Short (3pcs) | JC14: 3 | JD14: 4050 | JE14: 2594 | JF14: PWR 60's Choco / Free PT Short (3pcs) | JG14: 3 | JH14: 4050 | JI14: 2594 | JJ14: PWR 60's Choco / Free PT Short (3pcs) | JK14: 3 | JL14: 4050 | JM14: 2594 | JN14: PWR 60's Choco / Free PT Short (3pcs) | JO14: 3 | JP14: 4050 | JQ14: 2594 | JR14: PWR 60's Choco / Free PT Short (3pcs) | JS14: 3 | JT14: 4050 | JU14: 2594 | JV14: PWR 60's Choco / Free PT Short (3pcs) | JW14: 3 | JX14: 4050 | JY14: 2594 | JZ14: PWR 60's Choco / Free PT Short (3pcs) | KA14: 3 | KB14: 4050 | KC14: 2594 | KD14: PWR 60's Choco / Free PT Short (3pcs) | KE14: 3 | KF14: 4050 | KG14: 2594 | KH14: PWR 60's Choco / Free PT Short (3pcs) | KI14: 3 | KJ14: 4050 | KK14: 2594 | KL14: PWR 60's Choco / Free PT Short (3pcs) | KM14: 3 | KN14: 4050 | KO14: 2594 | KP14: PWR 60's Choco / Free PT Short (3pcs) | KQ14: 3 | KR14: 4050 | KS14: 2594 | KT14: PWR 60's Choco / Free PT Short (3pcs) | KU14: 3 | KV14: 4050 | KW14: 2594 | KX14: PWR 60's Choco / Free PT Short (3pcs) | KY14: 3 | KZ14: 4050 | LA14: 2594 | LB14: PWR 60's Choco / Free PT Short (3pcs) | LC14: 3 | LD14: 4050 | LE14: 2594 | LF14: PWR 60's Choco / Free PT Short (3pcs) | LG14: 3 | LH14: 4050 | LI14: 2594 | LJ14: PWR 60's Choco / Free PT Short (3pcs) | LK14: 3 | LL14: 4050 | LM14: 2594 | LN14: PWR 60's Choco / Free PT Short (3pcs) | LO14: 3 | LP14: 4050 | LQ14: 2594 | LR14: PWR 60's Choco / Free PT Short (3pcs) | LS14: 3 | LT14: 4050 | LU14: 2594 | LV14: PWR 60's Choco / Free PT Short (3pcs) | LW14: 3 | LX14: 4050 | LY14: 2594 | LZ14: PWR 60's Choco / Free PT Short (3pcs) | MA14: 3 | MB14: 4050 | MC14: 2594 | MD14: PWR 60's Choco / Free PT Short (3pcs) | ME14: 3 | MF14: 4050 | MG14: 2594 | MH14: PWR 60's Choco / Free PT Short (3pcs) | MI14: 3 | MJ14: 4050 | MK14: 2594 | ML14: PWR 60's Choco / Free PT Short (3pcs) | MM14: 3 | MN14: 4050 | MO14: 2594 | MP14: PWR 60's Choco / Free PT Short (3pcs) | MQ14: 3 | MR14: 4050 | MS14: 2594 | MT14: PWR 60's Choco / Free PT Short (3pcs) | MU14: 3 | MV14: 4050 | MW14: 2594 | MX14: PWR 60's Choco / Free PT Short (3pcs) | MY14: 3 | MZ14: 4050 | NA14: 2594 | NB14: PWR 60's Choco / Free PT Short (3pcs) | NC14: 3 | ND14: 4050 | NE14: 2594 | NF14: PWR 60's Choco / Free PT Short (3pcs) | NG14: 3 | NH14: 4050 | NI14: 2594 | NJ14: PWR 60's Choco / Free PT Short (3pcs) | NK14: 3 | NL14: 4050 | NM14: 2594 | NN14: PWR 60's Choco / Free PT Short (3pcs) | NO14: 3 | NP14: 4050 | NQ14: 2594 | NR14: PWR 60's Choco / Free PT Short (3pcs) | NS14: 3 | NT14: 4050 | NU14: 2594 | NV14: PWR 60's Choco / Free PT Short (3pcs) | NW14: 3 | NX14: 4050 | NY14: 2594 | NZ14: PWR 60's Choco / Free PT Short (3pcs) | OA14: 3 | OB14: 4050 | OC14: 2594 | OD14: PWR 60's Choco / Free PT Short (3pcs) | OE14: 3 | OF14: 4050 | OG14: 2594 | OH14: PWR 60's Choco / Free PT Short (3pcs) | OI14: 3 | OJ14: 4050 | OK14: 2594 | OL14: PWR 60's Choco / Free PT Short (3pcs) | OM14: 3 | ON14: 4050 | OO14: 2594 | OP14: PWR 60's Choco / Free PT Short (3pcs) | OQ14: 3 | OR14: 4050 | OS14: 2594 | OT14: PWR 60's Choco / Free PT Short (3pcs) | OU14: 3 | OV14: 4050 | OW14: 2594 | OX14: PWR 60's Choco / Free PT Short (3pcs) | OY14: 3 | OZ14: 4050 | PA14: 2594 | PB14: PWR 60's Choco / Free PT Short (3pcs) | PC14: 3 | PD14: 4050 | PE14: 2594 | PF14: PWR 60's Choco / Free PT Short (3pcs) | PG14: 3 | PH14: 4050 | PI14: 2594 | PJ14: PWR 60's Choco / Free PT Short (3pcs) | PK14: 3 | PL14: 4050 | PM14: 2594 | PN14: PWR 60's Choco / Free PT Short (3pcs) | PO14: 3 | PP14: 4050 | PQ14: 2594 | PR14: PWR 60's Choco / Free PT Short (3pcs) | PS14: 3 | PT14: 4050 | PU14: 2594 | PV14: PWR 60's Choco / Free PT Short (3pcs) | PW14: 3 | PX14: 4050 | PY14: 2594 | PZ14: PWR 60's Choco / Free PT Short (3pcs) | QA14: 3 | QB14: 4050 | QC14: 2594 | QD14: PWR 60's Choco / Free PT Short (3pcs) | QE14: 3 | QF14: 4050 | QG14: 2594 | QH14: PWR 60's Choco / Free PT Short (3pcs) | QI14: 3 | QJ14: 4050 | QK14: 2594 | QL14: PWR 60's Choco / Free PT Short (3pcs) | QM14: 3 | QN14: 4050 | QO14: 2594 | QP14: PWR 60's Choco / Free PT Short (3pcs) | QQ14: 3 | QR14: 4050 | QS14: 2594 | QT14: PWR 60's Choco / Free PT Short (3pcs) | QU14: 3 | QV14: 4050 | QW14: 2594 | QX14: PWR 60's Choco / Free PT Short (3pcs) | QY14: 3 | QZ14: 4050 | RA14: 2594 | RB14: PWR 60's Choco / Free PT Short (3pcs) | RC14: 3 | RD14: 4050 | RE14: 2594 | RF14: PWR 60's Choco / Free PT Short (3pcs) | RG14: 3 | RH14: 4050 | RI14: 2594 | RJ14: PWR 60's Choco / Free PT Short (3pcs) | RK14: 3 | RL14: 4050 | RM14: 2594 | RN14: PWR 60's Choco / Free PT Short (3pcs) | RO14: 3 | RP14: 4050 | RQ14: 2594 | RR14: PWR 60's Choco / Free PT Short (3pcs) | RS14: 3 | RT14: 4050 | RU14: 2594 | RV14: PWR 60's Choco / Free PT Short (3pcs) | RW14: 3 | RX14: 4050 | RY14: 2594 | RZ14: PWR 60's Choco / Free PT Short (3pcs) | SA14: 3 | SB14: 4050 | SC14: 2594 | SD14: PWR 60's Choco / Free PT Short (3pcs) | SE14: 3 | SF14: 4050 | SG14: 2594 | SH14: PWR 60's Choco / Free PT Short (3pcs) | SI14: 3 | SJ14: 4050 | SK14: 2594 | SL14: PWR 60's Choco / Free PT Short (3pcs) | SM14: 3 | SN14: 4050 | SO14: 2594 | SP14: PWR 60's Choco / Free PT Short (3pcs) | SQ14: 3 | SR14: 4050 | SS14: 2594 | ST14: PWR 60's Choco / Free PT Short (3pcs) | SU14: 3 | SV14: 4050 | SW14: 2594 | SX14: PWR 60's Choco / Free PT Short (3pcs) | SY14: 3 | SZ14: 4050 | TA14: 2594 | TB14: PWR 60's Choco / Free PT Short (3pcs) | TC14: 3 | TD14: 4050 | TE14: 2594 | TF14: PWR 60's Choco / Free PT Short (3pcs) | TG14: 3 | TH14: 4050 | TI14: 2594 | TJ14: PWR 60's Choco / Free PT Short (3pcs) | TK14: 3 | TL14: 4050 | TM14: 2594 | TN14: PWR 60's Choco / Free PT Short (3pcs) | TO14: 3 | TP14: 4050 | TQ14: 2594 | TR14: PWR 60's Choco / Free PT Short (3pcs) | TS14: 3 | TT14: 4050 | TU14: 2594 | TV14: PWR 60's Choco / Free PT Short (3pcs) | TW14: 3 | TX14: 4050 | TY14: 2594 | TZ14: PWR 60's Choco / Free PT Short (3pcs) | UA14: 3 | UB14: 4050 | UC14: 2594 | UD14: PWR 60's Choco / Free PT Short (3pcs) | UE14: 3 | UF14: 4050 | UG14: 2594 | UH14: PWR 60's Choco / Free PT Short (3pcs) | UI14: 3 | UJ14: 4050 | UK14: 2594 | UL14: PWR 60's Choco / Free PT Short (3pcs) | UM14: 3 | UN14: 4050 | UO14: 2594 | UP14: PWR 60's Choco / Free PT Short (3pcs) | UQ14: 3 | UR14: 4050 | US14: 2594 | UT14: PWR 60's Choco / Free PT Short (3pcs) | UU14: 3 | UV14: 4050 | UW14: 2594 | UX14: PWR 60's Choco / Free PT Short (3pcs) | UY14: 3 | UZ14: 4050 | VA14: 2594 | VB14: PWR 60's Choco / Free PT Short (3pcs) | VC14: 3 | VD14: 4050 | VE14: 2594 | VF14: PWR 60's Choco / Free PT Short (3pcs) | VG14: 3 | VH14: 4050 | VI14: 2594 | VJ14: PWR 60's Choco / Free PT Short (3pcs) | VK14: 3 | VL14: 4050 | VM14: 2594 | VN14: PWR 60's Choco / Free PT Short (3pcs) | VO14: 3 | VP14: 4050 | VQ14: 2594 | VR14: PWR 60's Choco / Free PT Short (3pcs) | VS14: 3 | VT14: 4050 | VU14: 2594 | VV14: PWR 60's Choco / Free PT Short (3pcs) | VW14: 3 | VX14: 4050 | VY14: 2594 | VZ14: PWR 60's Choco / Free PT Short (3pcs) | WA14: 3 | WB14: 4050 | WC14: 2594 | WD14: PWR 60's Choco / Free PT Short (3pcs) | WE14: 3 | WF14: 4050 | WG14: 2594 | WH14: PWR 60's Choco / Free PT Short (3pcs) | WI14: 3 | WJ14: 4050 | WK14: 2594 | WL14: PWR 60's Choco / Free PT Short (3pcs) | WM14: 3 | WN14: 4050 | WO14: 2594 | WP14: PWR 60's Choco / Free PT Short (3pcs) | WQ14: 3 | WR14: 4050 | WS14: 2594 | WT14: PWR 60's Choco / Free PT Short (3pcs) | WU14: 3 | WV14: 4050 | WW14: 2594 | WX14: PWR 60's Choco / Free PT Short (3pcs) | WY14: 3 | WZ14: 4050 | XA14: 2594 | XB14: PWR 60's Choco / Free PT Short (3pcs) | XC14: 3 | XD14: 4050 | XE14: 2594 | XF14: PWR 60's Choco / Free PT Short (3pcs) | XG14: 3 | XH14: 4050 | XI14: 2594 | XJ14: PWR 60's Choco / Free PT Short (3pcs) | XK14: 3 | XL14: 4050 | XM14: 2594 | XN14: PWR 60's Choco / Free PT Short (3pcs) | XO14: 3 | XP14: 4050 | XQ14: 2594 | XR14: PWR 60's Choco / Free PT Short (3pcs) | XS14: 3 | XT14: 4050 | XU14: 2594 | XV14: PWR 60's Choco / Free PT Short (3pcs) | XW14: 3 | XX14: 4050 | XY14: 2594 | XZ14: PWR 60's Choco / Free PT Short (3pcs) | YA14: 3 | YB14: 4050 | YC14: 2594 | YD14: PWR 60's Choco / Free PT Short (3pcs) | YE14: 3 | YF14: 4050 | YG14: 2594 | YH14: PWR 60's Choco / Free PT Short (3pcs) | YI14: 3 | YJ14: 4050 | YK14: 2594 | YL14: PWR 60's Choco / Free PT Short (3pcs) | YM14: 3 | YN14: 4050 | YO14: 2594 | YP14: PWR 60's Choco / Free PT Short (3pcs) | YQ14: 3 | YR14: 4050 | YS14: 2594 | YT14: PWR 60's Choco / Free PT Short (3pcs) | YU14: 3 | YV14: 4050 | YW14: 2594 | YX14: PWR 60's Choco / Free PT Short (3pcs) | YY14: 3 | YZ14: 4050 | ZA14: 2594 | ZB14: PWR 60's Choco / Free PT Short (3pcs) | ZC14: 3 | ZD14: 4050 | ZE14: 2594 | ZF14: PWR 60's Choco / Free PT Short (3pcs) | ZG14: 3 | ZH14: 4050 | ZI14: 2594 | ZJ14: PWR 60's Choco / Free PT Short (3pcs) | ZK14: 3 | ZL14: 4050 | ZM14: 2594 | ZN14: PWR 60's Choco / Free PT Short (3pcs) | ZO14: 3 | ZP14: 4050 | ZQ14: 2594 | ZR14: PWR 60's Choco / Free PT Short (3pcs) | ZS14: 3 | ZT14: 4050 | ZU14: 2594 | ZV14: PWR 60's Choco / Free PT Short (3pcs) | ZW14: 3 | ZX14: 4050 | ZY14: 2594 | ZZ14: PWR 60's Choco / Free PT Short (3pcs) | AAA14: 3 | AAB14: 4050 | AAC14: 2594 | AAD14: PWR 60's Choco / Free PT Short (3pcs) | AAE14: 3 | AAF14: 4050 | AAG14: 2594 | AAH14: PWR 60's Choco / Free PT Short (3pcs) | AAI14: 3 | AAJ14: 4050 | AAK14: 2594 | AAL14: PWR 60's Choco / Free PT Short (3pcs) | AAM14: 3 | AAN14: 4050 | AAO14: 2594 | AAP14: PWR 60's Choco / Free PT Short (3pcs) | AAQ14: 3 | AAR14: 4050 | AAS14: 2594 | AAT14: PWR 60's Choco / Free PT Short (3pcs) | AAU14: 3 | AAV14: 4050 | AAW14: 2594 | AAX14: PWR 60's Choco / Free PT Short (3pcs) | AAY14: 3 | AAZ14: 4050 | ABA14: 2594 | ABB14: PWR 60's Choco / Free PT Short (3pcs) | ABC14: 3 | ABD14: 4050 | ABE14: 2594 | ABF14: PWR 60's Choco / Free PT Short (3pcs) | ABG14: 3 | ABH14: 4050 | ABI14: 2594 | ABJ14: PWR 60's Choco / Free PT Short (3pcs) | ABK14: 3 | ABL14: 4050 | ABM14: 2594 | ABN14: PWR 60's Choco / Free PT Short (3pcs) | ABO14: 3 | ABP14: 4050 | ABQ14: 2594 | ABR14: PWR 60's Choco / Free PT Short (3pcs) | ABS14: 3 | ABT14: 4050 | ABU14: 2594 | ABV14: PWR 60's Choco / Free PT Short (3pcs) | ABW14: 3 | ABX14: 4050 | ABY14: 2594 | ABZ14: PWR 60's Choco / Free PT Short (3pcs) | ACA14: 3 | ACB14: 4050 | ACC14: 2594 | ACD14: PWR 60's Choco / Free PT Short (3pcs) | ACE14: 3 | ACF14: 4050 | ACG14: 2594 | ACH14: PWR 60's Choco / Free PT Short (3pcs) | ACI14: 3 | ACJ14: 4050 | ACK14: 2594 | ACL14: PWR 60's Choco / Free PT Short (3pcs) | ACM14: 3 | ACN14: 4050 | ACO14: 2594 | ACP14: PWR 60's Choco / Free PT Short (3pcs) | ACQ14: 3 | ACR14: 4050 | ACS14: 2594 | ACT14: PWR 60's Choco / Free PT Short (3pcs) | ACU14: 3 | ACV14: 4050 | ACW14: 2594 | ACX14: PWR 60's Choco / Free PT Short (3pcs) | ACY14: 3 | ACZ14: 4050 | ADA14: 2594 | ADB14: PWR 60's Choco / Free PT Short (3pcs) | ADC14: 3 | ADD14: 4050 | ADE14: 2594 | ADF14: PWR 60's Choco / Free PT Short (3pcs) | ADG14: 3 | ADH14: 4050 | ADI14: 2594 | ADJ14: PWR 60's Choco / Free PT Short (3pcs) | ADK14: 3 | ADL14: 4050 | ADM14: 2594 | ADN14: PWR 60's Choco / Free PT Short (3pcs) | ADO14: 3 | ADP14: 4050 | ADQ14: 2594 | ADR14: PWR 60's Choco / Free PT Short (3pcs) | ADS14: 3 | ADT14: 4050 | ADU14: 2594 | ADV14: PWR 60's Choco / Free PT Short (3pcs) | ADW14: 3 | ADX14: 4050 | ADY14: 2594 | ADZ14: PWR 60's Choco / Free PT Short (3pcs) | AEA14: 3 | AEB14: 4050 | AEC14: 2594 | AED14: PWR 60's Choco / Free PT Short (3pcs) | AEE14: 3 | AEF14: 4050 | AEG14: 2594 | AEH14: PWR 60's Choco / Free PT Short (3pcs) | AEI14: 3 | AEJ14: 4050 | AEK14: 2594 | AEL14: PWR 60's Choco / Free PT Short (3pcs) | AEM14: 3 | AEN14: 4050 | AEO14: 2594 | AEP14: PWR 60's Choco / Free PT Short (3pcs) | AEQ14: 3 | AER14: 4050 | AES14: 2594 | AET14: PWR 60's Choco / Free PT Short (3pcs) | AEU14: 3 | AEV14: 4050 | AEW14: 2594 | AEX14: PWR 60's Choco / Free PT Short (3pcs) | AEY14: 3 | AEZ14: 4050 | AFA14: 2594 | AFB14: PWR 60's Choco / Free PT Short (3pcs) | AFC14: 3 | AFD14: 4050 | AFE14: 2594 | AFF14: PWR 60's Choco / Free PT Short (3pcs) | AFG14: 3 | AFH14: 4050 | AFI14: 2594 | AFJ14: PWR 60's Choco / Free PT Short (3pcs) | AFK14: 3 | AFL14: 4050 | AFM14: 2594 | AFN14: PWR 60's Choco / Free PT Short (3pcs) | AFO14: 3 | AFP14: 4050 | AFQ14: 2594 | AFR14: PWR 60's Choco / Free PT Short (3pcs) | AFS14: 3 | AFT14: 4050 | AFU14: 2594 | AFV14: PWR 60's Choco / Free PT Short (3pcs) | AFW14: 3 | AFX14: 4050 | AFY14: 2594 | AFZ14: PWR 60's Choco / Free PT Short (3pcs) | AGA14: 3 | AGB14: 4050 | AGC14: 2594 | AGD14: PWR 60's Choco / Free PT Short (3pcs) | AGE14: 3 | AGF14: 4050 | AGG14: 2594 | AGH14: PWR 60's Choco / Free PT Short (3pcs) | AGI14: 3 | AGJ14: 4050 | AGK14: 2594 | AGL14: PWR 60's Choco / Free PT Short (3pcs) | AGM14: 3 | AGN14: 4050 | AGO14: 2594 | AGP14: PWR 60's Choco / Free PT Short (3pcs) | AGQ14: 3 | AGR14: 4050 | AGS14: 2594 | AGT14: PWR 60's Choco / Free PT Short (3pcs) | AGU14: 3 | AGV14: 4050 | AGW14: 2594 | AGX14: PWR 60's Choco / Free PT Short (3pcs) | AGY14: 3 | AGZ14: 4050 | AHA14: 2594 | AHB14: PWR 60's Choco / Free PT Short (3pcs) | AHC14: 3 | AHD14: 4050 | AHE14: 2594 | AHF14: PWR 60's Choco / Free PT Short (3pcs) | AHG14: 3 | AHH14: 4050 | AHI14: 2594 | AHJ14: PWR 60's Choco / Free PT Short (3pcs) | AHK14: 3 | AHL14: 4050 | AHM14: 2594 | AHN14: PWR 60's Choco / Free PT Short (3pcs) | AHO14: 3 | AHP14: 4050 | AHQ14: 2594 | AHR14: PWR 60's Choco / Free PT Short (3pcs) | AHS14: 3 | AHT14: 4050 | AHU14: 2594 | AHV14: PWR 60's Choco / Free PT Short (3pcs) | AHW14: 3 | AHX14: 4050 | AHY14: 2594 | AHZ14: PWR 60's Choco / Free PT Short (3pcs) | AIA14: 3 | AIB14: 4050 | AIC14: 2594 | AID14: PWR 60's Choco / Free PT Short (3pcs) | AIE14: 3 | AIF14: 4050 | AIG14: 2594 | AIH14: PWR 60's Choco / Free PT Short (3pcs) | AII14: 3 | AIJ14: 4050 | AIK14: 2594 | AIL14: PWR 60's Choco / Free PT Short (3pcs) | AIM14: 3 | AIN14: 4050 | AIO14: 2594 | AIP14: PWR 60's Choco / Free PT Short (3pcs) | AIQ14: 3 | AIR14: 4050 | AIS14: 2594 | AIT14: PWR 60's Choco / Free PT Short (3pcs) | AIU14: 3 | AIV14: 4050 | AIW14: 2594 | AIX14: PWR 60's Choco / Free PT Short (3pcs) | AIY14: 3 | AIZ14: 4050 | AJA14: 2594 | AJB14: PWR 60's Choco / Free PT Short (3pcs) | AJC14: 3 | AJD14: 4050 | AJE14: 2594 | AJF14: PWR 60's Choco / Free PT Short (3pcs) | AJG14: 3 | AJH14: 4050 | AJI14: 2594 | AJJ14: PWR 60's Choco / Free PT Short (3pcs) | AJK14: 3 | AJL14: 4050 | AJM14: 2594 | AJN14: PWR 60's Choco / Free PT Short (3pcs) | AJO14: 3 | AJP14: 4050 | AJQ14: 2594 | AJR14: PWR 60's Choco / Free PT Short (3pcs) | AJS14: 3 | AJT14: 4050 | AJU14: 2594 | AJV14: PWR 60's Choco / Free PT Short (3pcs) | AJW14: 3 | AJX14: 4050 | AJY14: 2594 | AJZ14: PWR 60's Choco / Free PT Short (3pcs) | AKA14: 3 | AKB14: 4050 | AKC14: 2594 | AKD14: PWR 60's Choco / Free PT Short (3pcs) | AKE14: 3 | AKF14: 4050 | AKG14: 2594 | AKH14: PWR 60's Choco / Free PT Short (3pcs) | AKI14: 3 | AKJ14: 4050 | AKK14: 2594 | AKL14: PWR 60's Choco / Free PT Short (3pcs) | AKM14: 3 | AKN14: 4050 | AKO14: 2594 | AKP14: PWR 60's Choco / Free PT Short (3pcs) | AKQ14: 3 | AKR14: 4050 | AKS14: 2594 | AKT14: PWR 60's Choco / Free PT Short (3pcs) | AKU14: 3 | AKV14: 4050 | AKW14: 2594 | AKX14: PWR 60's Choco / Free PT Short (3pcs) | AKY14: 3 | AKZ14: 4050 | ALA14: 2594 | ALB14: PWR 60's Choco / Free PT Short (3pcs) | ALC14: 3 | ALD14: 4050 | ALE14: 2594 | ALF14: PWR 60's Choco / Free PT Short (3pcs) | ALG14: 3 | ALH14: 4050 | ALI14: 2594 | ALJ14: PWR 60's Choco / Free PT Short (3pcs) | ALK14: 3 | ALL14: 4050 | ALM14: 2594 | ALN14: PWR 60's Choco / Free PT Short (3pcs) | ALO14: 3 | ALP14: 4050 | ALQ14: 2594 | ALR14: PWR 60's Choco / Free PT Short (3pcs) | ALS14: 3 | ALT14: 4050 | ALU14: 2594 | ALV14: PWR 60's Choco / Free PT Short (3pcs) | ALW14: 3 | ALX14: 4050 | ALY14: 2594 | ALZ14: PWR 60's Choco / Free PT Short (3pcs) | AMA14: 3 | AMB14: 4050 | AMC14: 2594 | AMD14: PWR 60's Choco / Free PT Short (3pcs) | AME14: 3 | AMF14: 4050 | AMG14: 2594 | AMH14: PWR 60's Choco / Free PT Short (3pcs) | AMI14: 3 | AMJ14: 4050 | AMK14: 2594 | AML14: PWR 60's Choco / Free PT Short (3pcs) | AMM14: 3 | AMN14: 4050 | AMO14: 2594 | AMP14: PWR 60's Choco / Free PT Short (3pcs) | AMQ14: 3 | AMR14: 4050 | AMS14: 2594 | AMT14: PWR 60's Choco / Free PT Short (3pcs) | AMU14: 3 | AMV14: 4050 | AMW14: 2594 | AMX14: PWR 60's Choco / Free PT Short (3pcs) | AMY14: 3 | AMZ14: 4050 | ANA14: 2594 | ANB14: PWR 60's Choco / Free PT Short (3pcs) | ANC14: 3 | AND14: 4050 | ANE14: 2594 | ANF14: PWR 60's Choco / Free PT Short (3pcs) | ANG14: 3 | ANH14: 4050 | ANI14: 2594 | ANJ14: PWR 60's Choco / Free PT Short (3pcs) | ANK14: 3 | ANL14: 4050 | ANM14: 2594 | ANN14: PWR 60's Choco / Free PT Short (3pcs) | ANO14: 3 | ANP14: 4050 | ANQ14: 2594 | ANR14: PWR 60's Choco / Free PT Short (3pcs) | ANS14: 3 | ANT14: 4050 | ANU14: 2594 | ANV14: PWR 60's Choco / Free PT Short (3pcs) | ANW14: 3 | ANX14: 4050 | ANY14: 2594 | ANZ14: PWR 60's Choco / Free PT Short (3pcs) | AOA14: 3 | AOB14: 4050 | AOC14: 2594 | AOD14: PWR 60's Choco / Free PT Short (3pcs) | AOE14: 3 | AOF14: 4050 | AOG14: 2594 | AOH14: PWR 60's Choco / Free PT Short (3pcs) | AOI14: 3 | AOJ14: 4050 | AOK14: 2594 | AOL14: PWR 60's Choco / Free PT Short (3pcs) | AOM14: 3 | AON14: 4050 | AOO14: 2594 | AOP14: PWR 60's Choco / Free PT Short (3pcs) | AOQ14: 3 | AOR14: 4050 | AOS14: 2594 | AOT14: PWR 60's Choco / Free PT Short (3pcs) | AOU14: 3 | AOV14: 4050 | AOW14: 2594 | AOX14: PWR 60's Choco / Free PT Short (3pcs) | AOY14: 3 | AOZ14: 4050 | APA14: 2594 | APB14: PWR 60's Choco / Free PT Short (3pcs) | APC14: 3 | APD14: 4050 | APE14: 2594 | APF14: PWR 60's Choco / Free PT Short (3pcs) | APG14: 3 | APH14: 4050 | API14: 2594 | APJ14: PWR 60's Choco / Free PT Short (3pcs) | APK14: 3 | APL14: 4050 | APM14: 2594 | APN14: PWR 60's Choco / Free PT Short (3pcs) | APO14: 3 | APP14: 4050 | APQ14: 2594 | APR14: PWR 60's Choco / Free PT Short (3pcs) | APS14: 3 | APT14: 4050 | APU14: 2594 | APV14: PWR 60's Choco / Free PT Short (3pcs) | APW14: 3 | APX14: 4050 | APY14: 2594 | APZ14: PWR 60's Choco / Free PT Short (3pcs) | AQA14: 3 | AQB14: 4050 | AQC14: 2594 | AQD14: PWR 60's Choco / Free PT Short (3pcs) | AQE14: 3 | AQF14: 4050 | AQG14: 2594 | AQH14: PWR 60's Choco / Free PT Short (3pcs) | AQI14: 3 | AQJ14: 4050 | AQK14: 2594 | AQL14: PWR 60's Choco / Free PT Short (3pcs) | AQM14: 3 | AQN14: 4050 | AQO14: 2594 | AQP14: PWR 60's Choco / Free PT Short (3pcs) | AQQ14: 3 | AQR14: 4050 | AQS14: 2594 | AQT14: PWR 60's Choco / Free PT Short (3pcs) | AQU14: 3 | AQV14: 4050 | AQW14: 2594 | AQX14: PWR 60's Choco / Free PT Short (3pcs) | AQY14: 3 | AQZ14: 4050 | ARA14: 2594 | ARB14: PWR 60's Choco / Free PT Short (3pcs) | ARC14: 3 | ARD14: 4050 | ARE14: 2594 | ARF14: PWR 60's Choco / Free PT Short (3pcs) | ARG14: 3 | ARH14: 4050 | ARI14: 2594 | ARJ14: PWR 60's Choco / Free PT Short (3pcs) | ARK14: 3 | ARL14: 4050 | ARM14: 2594 | ARN14: PWR 60's Choco / Free PT Short (3pcs) | ARO14: 3 | ARP14: 4050 | ARQ14: 2594 | ARR14: PWR 60's Choco / Free PT Short (3pcs) | ARS14: 3 | ART14: 4050 | ARU14: 2594 | ARV14: PWR 60's Choco / Free PT Short (3pcs) | ARW14: 3 | ARX14: 4050 | ARY14: 2594 | ARZ14: PWR 60's Choco / Free PT Short (3pcs) | ASA14: 3 | ASB14: 4050 | ASC14: 2594 | ASD14: PWR 60's Choco / Free PT Short (3pcs) | ASE14: 3 | ASF14: 4050 | ASG14: 2594 | ASH14: PWR 60's Choco / Free PT Short (3pcs) | ASI14: 3 | ASJ14: 4050 | ASK14: 2594 | ASL14: PWR 60's Choco / Free PT Short (3pcs) | ASM14: 3 | ASN14: 4050 | ASO14: 2594 | ASP14: PWR 60's Choco / Free PT Short (3pcs) | ASQ14: 3 | ASR14: 4050 | ASS14: 2594 | AST14: PWR 60's Choco / Free PT Short (3pcs) | ASU14: 3 | ASV14: 4050 | ASW14: 2594 | ASX14: PWR 60's Choco / Free PT Short (3pcs) | ASY14: 3 | ASZ14: 4050 | ATA14: 2594 | ATB14: PWR 60's Choco / Free PT Short (3pcs) | ATC14: 3 | ATD14: 4050 | ATE14: 2594 | ATF14: PWR 60's Choco / Free PT Short (3pcs) | ATG14: 3 | ATH14: 4050 | ATI14: 2594 | ATJ14: PWR 60's Choco / Free PT Short (3pcs) | ATK14: 3 | ATL14: 4050 | ATM14: 2594 | ATN14: PWR 60's Choco / Free PT Short (3pcs) | ATO14: 3 | ATP14: 4050 | ATQ14: 2594 | ATR14: PWR 60's Choco / Free PT Short (3pcs) | ATS14: 3 | ATT14: 4050 | ATU14: 2594 | ATV14: PWR 60's Choco / Free PT Short (3pcs) | ATW14: 3 | ATX14: 4050 | ATY14: 2594 | ATZ14: PWR 60's Choco / Free PT Short (3pcs) | AUA14: 3 | AUB14: 4050 | AUC14: 2594 | AUD14: PWR 60's Choco / Free PT Short (3pcs) | AUE14: 3 | AUF14: 4050 | AUG14: 2594 | AUH14: PWR 60's Choco / Free PT Short (3pcs) | AUI14: 3 | AUJ14: 4050 | AUK14: 2594 | AUL14: PWR 60's Choco / Free PT Short (3pcs) | AUM14: 3 | AUN14: 4050 | AUO14: 2594 | AUP14: PWR 60's Choco / Free PT Short (3pcs) | AUQ14: 3 | AUR14: 4050 | AUS14: 2594 | AUT14: PWR 60's Choco / Free PT Short (3pcs) | AUU14: 3 | AUV14: 4050 | AUW14: 2594 | AUX14: PWR 60's Choco / Free PT Short (3pcs) | AUY14: 3 | AUZ14: 4050 | AVA14: 2594 | AVB14: PWR 60's Choco / Free PT Short (3pcs) | AVC14: 3 | AVD14: 4050 | AVE14: 2594 | AVF14: PWR 60's Choco / Free PT Short (3pcs) | AVG14: 3 | AVH14: 4050 | AVI14: 2594 | AVJ14: PWR 60's Choco / Free PT Short (3pcs) | AVK14: 3 | AVL14: 4050 | AVM14: 2594 | AVN14: PWR 60's Choco / Free PT Short (3pcs) | AVO14: 3 | AVP14: 4050 | AVQ14: 2594 | AVR14: PWR 60's Choco / Free PT Short (3pcs) | AVS14: 3 | AVT14: 4050 | AVU14: 2594 | AVV14: PWR 60's Choco / Free PT Short (3pcs) | AVW14: 3 | AVX14: 4050 | AVY14: 2594 | AVZ14: PWR 60's Choco / Free PT Short (3pcs) | AWA14: 3 | AWB14: 4050 | AWC14: 2594 | AWD14: PWR 60's Choco / Free PT Short (3pcs) | AWE14: 3 | AWF14: 4050 | AWG14: 2594 | AWH14: PWR 60's Choco / Free PT Short (3pcs) | AWI14: 3 | AWJ14: 4050 | AWK14: 2594 | AWL14: PWR 60's Choco / Free PT Short (3pcs) | AWM14: 3 | AWN14: 4050 | AWO14: 2594 | AWP14: PWR 60's Choco / Free PT Short (3pcs) | AWQ14: 3 | AWR14: 4050 | AWS14: 2594 | AWT14: PWR 60's Choco / Free PT Short (3pcs) | AWU14: 3 | AWV14: 4050 | AWW14: 2594 | AWX14: PWR 60's Choco / Free PT Short (3pcs) | AWY14: 3 | AWZ14: 4050 | AXA14: 2594 | AXB14: PWR 60's Choco / Free PT Short (3pcs) | AXC14: 3 | AXD14: 4050 | AXE14: 2594 | AXF14: PWR 60's Choco / Free PT Short (3pcs) | AXG14: 3 | AXH14: 4050 | AXI14: 2594 | AXJ14: PWR 60's Choco / Free PT Short (3pcs) | AXK14: 3 | AXL14: 4050 | AXM14: 2594 | AXN14: PWR 60's Choco / Free PT Short (3pcs) | AXO14: 3 | AXP14: 4050 | AXQ14: 2594 | AXR14: PWR 60's Choco / Free PT Short (3pcs) | AXS14: 3 | AXT14: 4050 | AXU14: 2594 | AXV14: PWR 60's Choco / Free PT Short (3pcs) | AXW14: 3 | AXX14: 4050 | AXY14: 2594 | AXZ14: PWR 60's Choco / Free PT Short (3pcs) | AYA14: 3 | AYB14: 4050 | AYC14: 2594 | AYD14: PWR 60's Choco / Free PT Short (3pcs) | AYE14: 3 | AYF14: 4050 | AYG14: 2594 | AYH14: PWR 60's Choco / Free PT Short (3pcs) | AYI14: 3 | AYJ14: 4050 | AYK14: 2594 | AYL14: PWR 60's Choco / Free PT Short (3pcs) | AYM14: 3 | AYN14: 4050 | AYO14: 2594 | AYP14: PWR 60's Choco / Free PT Short (3pcs) | AYQ14: 3 | AYR14: 4050 | AYS14: 2594 | AYT14: PWR 60's Choco / Free PT Short (3pcs) | AYU14: 3 | AYV14: 4050 | AYW14: 2594 | AYX14: PWR 60's Choco / Free PT Short (3pcs) | AYY14: 3 | AYZ14: 4050 | AZA14: 2594 | AZB14: PWR 60's Choco / Free PT Short (3pcs) | AZC14: 3 | AZD14: 4050 | AZE14: 2594 | AZF14: PWR 60's Choco / Free PT Short (3pcs) | AZG14: 3 | AZH14: 4050 | AZI14: 2594 | AZJ14: PWR 60's Choco / Free PT Short (3pcs) | AZK14: 3 | AZL14: 4050 | AZM14: 2594 | AZN14: PWR 60's Choco / Free PT Short (3pcs) | AZO14: 3 | AZP14: 4050 | AZQ14: 2594 | AZR14: PWR 60's Choco / Free PT Short (3pcs) | AZS14: 3 | AZT14: 4050 | AZU14: 2594 | AZV14: PWR 60's Choco / Free PT Short (3pcs) | AZW14: 3 | AZX14: 4050 | AZY14: 2594 | AZZ14: PWR 60's Choco / Free PT Short (3pcs) | BAA14: 3 | BAB14: 4050 | BAC14: 2594 | BAD14: PWR 60's Choco / Free PT Short (3pcs) | BAE14: 3 | BAF14: 4050 | BAG14: 2594 | BAH14: PWR 60's Choco / Free PT Short (3pcs) | BAI14: 3 | BAJ14: 4050 | BAK14: 2594 | BAL14: PWR 60's Choco / Free PT Short (3pcs) | BAM14: 3 | BAN14: 4050 | BAO14: 2594 | BAP14: PWR 60's Choco / Free PT Short (3pcs) | BAQ14: 3 | BAR14: 4050 | BAS14: 2594 | BAT14: PWR 60's Choco / Free PT Short (3pcs) | BAU14: 3 | BAV14: 4050 | BAW14: 2594 | BAX14: PWR 60's Choco / Free PT Short (3pcs) | BAY14: 3 | BAZ14: 4050 | BBA14: 2594 | BBB14: PWR 60's Choco / Free PT Short (3pcs) | BBC14: 3 | BBD14: 4050 | BBE14: 2594 | BBF14: PWR 60's Choco / Free PT Short (3pcs) | BBG14: 3 | BBH14: 4050 | BBI14: 2594 | BBJ14: PWR 60's Choco / Free PT Short (3pcs) | BBK14: 3 | BBL14: 4050 | BBM14: 2594 | BBN14: PWR 60's Choco / Free PT Short (3pcs) | BBO14: 3 | BBP14: 4050 | BBQ14: 2594 | BBR14: PWR 60's Choco / Free PT Short (3pcs) | BBS14: 3 | BBT14: 4050 | BBU14: 2594 | BBV14: PWR 60's Choco / Free PT Short (3pcs) | BBW14: 3 | BBX14: 4050 | BBY14: 2594 | BBZ14: PWR 60's Choco / Free PT Short (3pcs) | BCA14: 3 | BCB14: 4050 | BCC14: 2594 | BCD14: PWR 60's Choco / Free PT Short (3pcs) | BCE14: 3 | BCF14: 4050 | BCG14: 2594 | BCH14: PWR 60's Choco / Free PT Short (3pcs) | BCI14: 3 | BCJ14: 4050 | BCK14: 2594 | BCL14: PWR 60's Choco / Free PT Short (3pcs) | BCM14: 3 | BCN14: 4050 | BCO14: 2594 | BCP14: PWR 60's Choco / Free PT Short (3pcs) | BCQ14: 3 | BCR14: 4050 | BCS14: 2594 | BCT14: PWR 60's Choco / Free PT Short (3pcs) | BCU14: 3 | BCV14: 4050 | BCW14: 2594 | BCX14: PWR 60's Choco / Free PT Short (3pcs) | BCY14: 3 | BCZ14: 4050 | BDA14: 2594 | BDB14: PWR 60's Choco / Free PT Short (3pcs) | BDC14: 3 | BDD14: 4050 | BDE14: 2594 | BDF14: PWR 60's Choco / Free PT Short (3pcs) | BDG14: 3 | BDH14: 4050 | BDI14: 2594 | BDJ14: PWR 60's Choco / Free PT Short (3pcs) | BDK14: 3 | BDL14: 4050 | BDM14: 2594 | BDN14: PWR 60's Choco / Free PT Short (3pcs) | BDO14: 3 | BDP14: 4050 | BDQ14: 2594 | BDR14: PWR 60's Choco / Free PT Short (3pcs) | BDS14: 3 | BDT14: 4050 | BDU14: 2594 | BDV14: PWR 60's Choco / Free PT Short (3pcs) | BDW14: 3 | BDX14: 4050 | BDY14: 2594 | BDZ14: PWR 60's Choco / Free PT Short (3pcs) | BEA14: 3 | BEB14: 4050 | BEC14: 2594 | BED14: PWR 60's Choco / Free PT Short (3pcs) | BEE14: 3 | BEF14: 4050 | BEG14: 2594 | BEH14: PWR 60's Choco / Free PT Short (3pcs) | BEI14: 3 | BEJ14: 4050 | BEK14: 2594 | BEL14: PWR 60's Choco / Free PT Short (3pcs) | BEM14: 3 | BEN14: 4050 | BEO14: 2594 | BEP14: PWR 60's Choco / Free PT Short (3pcs) | BEQ14: 3 | BER14: 4050 | BES14: 2594 | BET14: PWR 60's Choco / Free PT Short (3pcs) | BEU14: 3 | BEV14: 4050 | BEW14: 2594 | BEX14: PWR 60's Choco / Free PT Short (3pcs) | BEY14: 3 | BEZ14: 4050 | BFA14: 2594 | BFB14: PWR 60's Choco / Free PT Short (3pcs) | BFC14: 3 | BFD14: 4050 | BFE14: 2594 | BFF14: PWR 60's Choco / Free PT Short (3pcs) | BFG14: 3 | BFH14: 4050 | BFI14: 2594 | BFJ14: PWR 60's Choco / Free PT Short (3pcs) | BFK14: 3 | BFL14: 4050 | BFM14: 2594 | BFN14: PWR 60's Choco / Free PT Short (3pcs) | BFO14: 3 | BFP14: 4050 | BFQ14: 2594 | BFR14: PWR 60's Choco / Free PT Short (3pcs) | BFS14: 3 | BFT14: 4050 | BFU14: 2594 | BFV14: PWR 60's Choco / Free PT Short (3pcs) | BFW14: 3 | BFX14: 4050 | BFY14: 2594 | BFZ14: PWR 60's Choco / Free PT Short (3pcs) | BGA14: 3 | BGB14: 4050 | BGC14: 2594 | BGD14: PWR 60's Choco / Free PT Short (3pcs) | BGE14: 3 | BGF14: 4050 | BGG14: 2594 | BGH14: PWR 60's Choco / Free PT Short (3pcs) | BGI14: 3 | BGJ14: 4050 | BGK14: 2594 | BGL14: PWR 60's Choco / Free PT Short (3pcs) | BGM14: 3 | BGN14: 4050 | BGO14: 2594 | BGP14: PWR 60's Choco / Free PT Short (3pcs) | BGQ14: 3 | BGR14: 4050 | BGS14: 2594 | BGT14: PWR 60's Choco / Free PT Short (3pcs) | BGU14: 3 | BGV14: 4050 | BGW14: 2594 | BGX14: PWR 60's Choco / Free PT Short (3pcs) | BGY14: 3 | BGZ14: 4050 | BHA14: 2594 | BHB14: PWR 60's Choco / Free PT Short (3pcs) | BHC14: 3 | BHD14: 4050 | BHE14: 2594 | BHF14: PWR 60's Choco / Free PT Short (3pcs) | BHG14: 3 | BHH14: 4050 | BHI14: 2594 | BHJ14: PWR 60's Choco / Free PT Short (3pcs) | BHK14: 3 | BHL14: 4050 | BHM14: 2594 | BHN14: PWR 60's Choco / Free PT Short (3pcs) | BHO14: 3 | BHP14: 4050 | BHQ14: 2594 | BHR14: PWR 60's Choco / Free PT Short (3pcs) | BHS14: 3 | BHT14: 4050 | BHU14: 2594 | BHV14: PWR 60's Choco / Free PT Short (3pcs) | BHW14: 3 | BHX14: 4050 | BHY14: 2594 | BHZ14: PWR 60's Choco / Free PT Short (3pcs) | BIA14: 3 | BIB14: 4050 | BIC14: 2594 | BID14: PWR 60's Choco / Free PT Short (3pcs) | BIE14: 3 | BIF14: 4050 | BIG14: 2594 | BIH14: PWR 60's Choco / Free PT Short (3pcs) | BII14: 3 | BIJ14: 4050 | BIK14: 2594 | BIL14: PWR 60's Choco / Free PT Short (3pcs) | BIM14: 3 | BIN14: 4050 | BIO14: 2594 | BIP14: PWR 60's Choco / Free PT Short (3pcs) | BIQ14: 3 | BIR14: 4050 | BIS14: 2594 | BIT14: PWR 60's Choco / Free PT Short (3pcs) | BIU14: 3 | BIV14: 4050 | BIW14: 2594 | BIX14: PWR 60's Choco / Free PT Short (3pcs) | BIY14: 3 | BIZ14: 4050 | BJA14: 2594 | BJB14: PWR 60's Choco / Free PT Short (3pcs) | BJC14: 3 | BJD14: 4050 | BJE14: 2594 | BJF14: PWR 60's Choco / Free PT Short (3pcs) | BJG14: 3 | BJH14: 4050 | BJI14: 2594 | BJJ14: PWR 60's Choco / Free PT Short (3pcs) | BJK14: 3 | BJL14: 4050 | BJM14: 2594 | BJN14: PWR 60's Choco / Free PT Short (3pcs) | BJO14: 3 | BJP14: 4050 | BJQ14: 2594 | BJR14: PWR 60's Choco / Free PT Short (3pcs) | BJS14: 3 | BJT14: 4050 | BJU14: 2594 | BJV14: PWR 60's Choco / Free PT Short (3pcs) | BJW14: 3 | BJX14: 4050 | BJY14: 2594 | BJZ14: PWR 60's Choco / Free PT Short (3pcs) | BKA14: 3 | BKB14: 4050 | BKC14: 2594 | BKD14: PWR 60's Choco / Free PT Short (3pcs) | BKE14: 3 | BKF14: 4050 | BKG14: 2594 | BKH14: PWR 60's Choco / Free PT Short (3pcs) | BKI14: 3 | BKJ14: 4050 | BKK14: 2594 | BKL14: PWR 60's Choco / Free PT Short (3pcs) | BKM14: 3 | BKN14: 4050 | BKO14: 2594 | BKP14: PWR 60's Choco / Free PT Short (3pcs) | BKQ14: 3 | BKR14: 4050 | BKS14: 2594 | BKT14: PWR 60's Choco / Free PT Short (3pcs) | BKU14: 3 | BKV14: 4050 | BKW14: 2594 | BKX14: PWR 60's Choco / Free PT Short (3pcs) | BKY14: 3 | BKZ14: 4050 | BLA14: 2594 | BLB14: PWR 60's Choco / Free PT Short (3pcs) | BLC14: 3 | BLD14: 4050 | BLE14: 2594 | BLF14: PWR 60's Choco / Free PT Short (3pcs) | BLG14: 3 | BLH14: 4050 | BLI14: 2594 | BLJ14: PWR 60's Choco / Free PT Short (3pcs) | BLK14: 3 | BLL14: 4050 | BLM14: 2594 | BLN14: PWR 60's Choco / Free PT Short (3pcs) | BLO14: 3 | BLP14: 4050 | BLQ14: 2594 | BLR14: PWR 60's Choco / Free PT Short (3pcs) | BLS14: 3 | BLT14: 4050 | BLU14: 2594 | BLV14: PWR 60's Choco / Free PT Short (3pcs) | BLW14: 3 | BLX14: 4050 | BLY14: 2594 | BLZ14: PWR 60's Choco / Free PT Short (3pcs) | BMA14: 3 | BMB14: 4050 | BMC14: 2594 | BMD14: PWR 60's Choco / Free PT Short (3pcs) | BME14: 3 | BMF14: 4050 | BMG14: 2594 | BMH14: PWR 60's Choco / Free PT Short (3pcs) | BMI14: 3 | BMJ14: 4050 | BMK14: 2594 | BML14: PWR 60's Choco / Free PT Short (3pcs) | BMM14: 3 | BMN14: 4050 | BMO14: 2594 | BMP14: PWR 60's Choco / Free PT Short (3pcs) | BMQ14: 3 | BMR14: 4050 | BMS14: 2594 | BMT14: PWR 60's Choco / Free PT Short (3pcs) | BMU14: 3 | BMV14: 4050 | BMW14: 2594 | BMX14: PWR 60's Choco / Free PT Short (3pcs) | BMY14: 3 | BMZ14: 4050 | BNA14: 2594 | BNB14: PWR 60's Choco / Free PT Short (3pcs) | BNC14: 3 | BND14: 4050 | BNE14: 2594 | BNF14: PWR 60's Choco / Free PT Short (3pcs) | BNG14: 3 | BNH14: 4050 | BNI14: 2594 | BNJ14: PWR 60's Choco / Free PT Short (3pcs) | BNK14: 3 | BNL14: 4050 | BNM14: 2594 | BNN14: PWR 60's Choco / Free PT Short (3pcs) | BNO14: 3 | BNP14: 4050 | BNQ14: 2594 | BNR14: PWR 60's Choco / Free PT Short (3pcs) | BNS14: 3 | BNT14: 4050 | BNU14: 2594 | BNV14: PWR 60's Choco / Free PT Short (3pcs) | BNW14: 3 | BNX14: 4050 | BNY14: 2594 | BNZ14: PWR 60's Choco / Free PT Short (3pcs) | BOA14: 3 | BOB14: 4050 | BOC14: 2594 | BOD14: PWR 60's Choco / Free PT Short (3pcs) | BOE14: 3 | BOF14: 4050 | BOG14: 2594 | BOH14: PWR 60's Choco / Free PT Short (3pcs) | BOI14: 3 | BOJ14: 4050 | BOK14: 2594 | BOL14: PWR 60's Choco / Free PT Short (3pcs) | BOM14: 3 | BON14: 4050 | BOO14: 2594 | BOP14: PWR 60's Choco / Free PT Short (3pcs) | BOQ14: 3 | BOR14: 4050 | BOS14: 2594 | BOT14: PWR 60's Choco / Free PT Short (3pcs) | BOU14: 3 | BOV14: 4050 | BOW14: 2594 | BOX14: PWR 60's Choco / Free PT Short (3pcs) | BOY14: 3 | BOZ14: 4050 | BPA14: 2594 | BPB14: PWR 60's Choco / Free PT Short (3pcs) | BPC14: 3 | BPD14: 4050 | BPE14: 2594 | BPF14: PWR 60's Choco / Free PT Short (3pcs) | BPG14: 3 | BPH14: 4050 | BPI14: 2594 | BPJ14: PWR 60's Choco / Free PT Short (3pcs) | BPK14: 3 | BPL14: 4050 | BPM14: 2594 | BPN14: PWR 60's Choco / Free PT Short (3pcs) | BPO14: 3 | BPP14: 4050 | BPQ14: 2594 | BPR14: PWR 60's Choco / Free PT Short (3pcs) | BPS14: 3 | BPT14: 4050 | BPU14: 2594 | BPV14: PWR 60's Choco / Free PT Short (3pcs) | BPW14: 3 | BPX14: 4050 | BPY14: 2594 | BPZ14: PWR 60's Choco / Free PT Short (3pcs) | BQA14: 3 | BQB14: 4050 | BQC14: 2594 | BQD14: PWR 60's Choco / Free PT Short (3pcs) | BQE14: 3 | BQF14: 4050 | BQG14: 2594 | BQH14: PWR 60's Choco / Free PT Short (3pcs) | BQI14: 3 | BQJ14: 4050 | BQK14: 2594 | BQL14: PWR 60's Choco / Free PT Short (3pcs) | BQM14: 3 | BQN14: 4050 | BQO14: 2594 | BQP14: PWR 60's Choco / Free PT Short (3pcs) | BQQ14: 3 | BQR14: 4050 | BQS14: 2594 | BQT14: PWR 60's Choco / Free PT Short (3pcs) | BQU14: 3 | BQV14: 4050 | BQW14: 2594 | BQX14: PWR 60's Choco / Free PT Short (3pcs) | BQY14: 3 | BQZ14: 4050 | BRA14: 2594 | BRB14: PWR 60's Choco / Free PT Short (3pcs) | BRC14: 3 | BRD14: 4050 | BRE14: 2594 | BRF14: PWR 60's Choco / Free PT Short (3pcs) | BRG14: 3 | BRH14: 4050 | BRI14: 2594 | BRJ14: PWR 60's Choco / Free PT Short (3pcs) | BRK14: 3 | BRL14: 4050 | BRM14: 2594 | BRN14: PWR 60's Choco / Free PT Short (3pcs) | BRO14: 3 | BRP14: 4050 | BRQ14: 2594 | BRR14: PWR 60's Choco / Free PT Short (3pcs) | BRS14: 3 | BRT14: 4050 | BRU14: 2594 | BRV14: PWR 60's Choco / Free PT Short (3pcs) | BRW14: 3 | BRX14: 4050 | BRY14: 2594 | BRZ14: PWR 60's Choco / Free PT Short (3pcs) | BSA14: 3 | BSB14: 4050 | BSC14: 2594 | BSD14: PWR 60's Choco / Free PT Short (3pcs) | BSE14: 3 | BSF14: 4050 | BSG14: 2594 | BSH14: PWR 60's Choco / Free PT Short (3pcs) | BSI14: 3 | BSJ14: 4050 | BSK14: 2594 | BSL14: PWR 60's Choco / Free PT Short (3pcs) | BSM14: 3 | BSN14: 4050 | BSO14: 2594 | BSP14: PWR 60's Choco / Free PT Short (3pcs) | BSQ14: 3 | BSR14: 4050 | BSS14: 2594 | BST14: PWR 60's Choco / Free PT Short (3pcs) | BSU14: 3 | BSV14: 4050 | BSW14: 2594 | BSX14: PWR 60's Choco / Free PT Short (3pcs) | BSY14: 3 | BSZ14: 4050 | BTA14: 2594 | BTB14: PWR 60's Choco / Free PT Short (3pcs) | BTC14: 3 | BTD14: 4050 | BTE14: 2594 | BTF14: PWR 60's Choco / Free PT Short (3pcs) | BTG14: 3 | BTH14: 4050 | BTI14: 2594 | BTJ14: PWR 60's Choco / Free PT Short (3pcs) | BTK14: 3 | BTL14: 4050 | BTM14: 2594 | BTN14: PWR 60's Choco / Free PT Short (3pcs) | BTO14: 3 | BTP14: 4050 | BTQ14: 2594 | BTR14: PWR 60's Choco / Free PT Short (3pcs) | BTS14: 3 | BTT14: 4050 | BTU14: 2594 | BTV14: PWR 60's Choco / Free PT Short (3pcs) | BTW14: 3 | BTX14: 4050 | BTY14: 2594 | BTZ14: PWR 60's Choco / Free PT Short (3pcs) | BUA14: 3 | BUB14: 4050 | BUC14: 2594 | BUD14: PWR 60's Choco / Free PT Short (3pcs) | BUE14: 3 | BUF14: 4050 | BUG14: 2594 | BUH14: PWR 60's Choco / Free PT Short (3pcs) | BUI14: 3 | BUJ14: 4050 | BUK14: 2594 | BUL14: PWR 60's Choco / Free PT Short (3pcs) | BUM14: 3 | BUN14: 4050 | BUO14: 2594 | BUP14: PWR 60's Choco / Free PT Short (3pcs) | BUQ14: 3 | BUR14: 4050 | BUS14: 2594 | BUT14: PWR 60's Choco / Free PT Short (3pcs) | BUU14: 3 | BUV14: 4050 | BUW14: 2594 | BUX14: PWR 60's Choco / Free PT Short (3pcs) | BUY14: 3 | BUZ14: 4050 | BVA14: 2594 | BVB14: PWR 60's Choco / Free PT Short (3pcs) | BVC14: 3 | BVD14: 4050 | BVE14: 2594 | BVF14: PWR 60's Choco / Free PT Short (3pcs) | BVG14: 3 | BVH14: 4050 | BVI14: 2594 | BVJ14: PWR 60's Choco / Free PT Short (3pcs) | BVK14: 3 | BVL14: 4050 | BVM14: 2594 | BVN14: PWR 60's Choco / Free PT Short (3pcs) | BVO14: 3 | BVP14: 4050 | BVQ14: 2594 | BVR14: PWR 60's Choco / Free PT Short (3pcs) | BVS14: 3 | BVT14: 4050 | BVU14: 2594 | BVV14: PWR 60's Choco / Free PT Short (3pcs) | BVW14: 3 | BVX14: 4050 | BVY14: 2594 | BVZ14: PWR 60's Choco / Free PT Short (3pcs) | BWA14: 3 | BWB14: 4050 | BWC14: 2594 | BWD14: PWR 60's Choco / Free PT Short (3pcs) | BWE14: 3 | BWF14: 4050 | BWG14: 2594 | BWH14: PWR 60's Choco / Free PT Short (3pcs) | BWI14: 3 | BWJ14: 4050 | BWK14: 2594 | BWL14: PWR 60's Choco / Free PT Short (3pcs) | BWM14: 3 | BWN14: 4050 | BWO14: 2594 | BWP14: PWR 60's Choco / Free PT Short (3pcs) | BWQ14: 3 | CGB14: 4050 | CGC14: 2594 | CGD14: PWR 60's Choco / Free PT Short (3pcs) | CGE14: 3 | CGF14: 4050 | CGG14: 2594 | CGH14: PWR 60's Choco / Free PT Short (3pcs) | CGI14: 3 | CGJ14: 4050 | CGK14: 2594 | CGL14: PWR 60's Choco / Free PT Short (3pcs) | CGM14: 3 | CGN14: 4050 | CGO14: 2594 | CGP14: PWR 60's Choco / Free PT Short (3pcs) | CGQ14: 3 | CGR14: 4050 | CGS14: 2594 | CGT14: PWR 60's Choco / Free PT Short (3pcs) | CGU14: 3 | CGV14: 4050 | CGW14: 2594 | CGX14: PWR 60's Choco / Free PT Short (3pcs) | CGY14: 3 | CGZ14: 4050 | CHA14: 2594 | CHB14: PWR 60's Choco / Free PT Short (3pcs) | CHC14: 3 | CHD14: 4050 | CHE14: 2594 | CHF14: PWR 60's Choco / Free PT Short (3pcs) | CHG14: 3 | CHH14: 4050 | CHI14: 2594 | CHJ14: PWR 60's Choco / Free PT Short (3pcs) | CHK14: 3 | CHL14: 4050 | CHM14: 2594 | CHN14: PWR 60's Choco / Free PT Short (3pcs) | CHO14: 3 | CHP14: 4050 | CHQ14: 2594 | CHR14: PWR 60's Choco / Free PT Short (3pcs) | CHS14: 3 | CHT14: 4050 | CHU14: 2594 | CHV14: PWR 60's Choco / Free PT Short (3pcs) | CHW14: 3 | CHX14: 4050 | CHY14: 2594 | CHZ14: PWR 60's Choco / Free PT Short (3pcs) | CIA14: 3 | CIB14: 4050 | CIC14: 2594 | CID14: PWR 60's Choco / Free PT Short (3pcs) | CIE14: 3 | CIF14: 4050 | CIG14: 2594 | CIH14: PWR 60's Choco / Free PT Short (3pcs) | CII14: 3 | CIJ14: 4050 | CIK14: 2594 | CIL14: PWR 60's Choco / Free PT Short (3pcs) | CIM14: 3 | CIN14: 4050 | CIO14: 2594 | CIP14: PWR 60's Choco / Free PT Short (3pcs) | CIQ14: 3 | CIR14: 4050 | CIS14: 2594 | CIT14: PWR 60's Choco / Free PT Short (3pcs) | CIU14: 3 | CIV14: 4050 | CIW14: 2594 | CIX14: PWR 60's Choco / Free PT Short (3pcs) | CIY14: 3 | CIZ14: 4050 | CJA14: 2594 | CJB14: PWR 60's Choco / Free PT Short (3pcs) | CJC14: 3 | CJD14: 4050 | CJE14: 2594 | CJF14: PWR 60's Choco / Free PT Short (3pcs) | CJG14: 3 | CJH14: 4050 | CJI14: 2594 | CJJ14: PWR 60's Choco / Free PT Short (3pcs) | CJK14: 3 | CJL14: 4050 | CJM14: 2594 | CJN14: PWR 60's Choco / Free PT Short (3pcs) | CJO14: 3 | CJP14: 4050 | CJQ14: 2594 | CJR14: PWR 60's Choco / Free PT Short (3pcs) | CJS14: 3 | CJT14: 4050 | CJU14: 2594 | CJV14: PWR 60's Choco / Free PT Short (3pcs) | CJW14: 3 | CJX14: 4050 | CJY14: 2594 | CJZ14: PWR 60's Choco / Free PT Short (3pcs) | CKA14: 3 | CKB14: 4050 | CKC14: 2594 | CKD14: PWR 60's Choco / Free PT Short (3pcs) | CKE14: 3 | CKF14: 4050 | CKG14: 2594 | CKH14: PWR 60's Choco / Free PT Short (3pcs) | CKI14: 3 | CKJ14: 4050 | CKK14: 2594 | CKL14: PWR 60's Choco / Free PT Short (3pcs) | CKM14: 3 | CKN14: 4050 | CKO14: 2594 | CKP14: PWR 60's Choco / Free PT Short (3pcs) | CKQ14: 3 | CKR14: 4050 | CKS14: 2594 | CKT14: PWR 60's Choco / Free PT Short (3pcs) | CKU14: 3 | CKV14: 4050 | CKW14: 2594 | CKX14: PWR 60's Choco / Free PT Short (3pcs) | CKY14: 3 | CKZ14: 4050 | CLA14: 2594 | CLB14: PWR 60's Choco / Free PT Short (3pcs) | CLC14: 3 | CLD14: 4050 | CLE14: 2594 | CLF14: PWR 60's Choco / Free PT Short (3pcs) | CLG14: 3 | CLH14: 4050 | CLI14: 2594 | CLJ14: PWR 60's Choco / Free PT Short (3pcs) | CLK14: 3 | CLL14: 4050 | CLM14: 2594 | CLN14: PWR 60's Choco / Free PT Short (3pcs) | CLO14: 3 | CLP14: 4050 | CLQ14: 2594 | CLR14: PWR 60's Choco / Free PT Short (3pcs) | CLS14: 3 | CLT14: 4050 | CLU14: 2594 | CLV14: PWR 60's Choco / Free PT Short (3pcs) | CLW14: 3 | CLX14: 4050 | CLY14: 2594 | CLZ14: PWR 60's Choco / Free PT Short (3pcs) | CMA14: 3 | CMB14: 4050 | CMC14: 2594 | CMD14: PWR 60's Choco / Free PT Short (3pcs) | CME14: 3 | CMF14: 4050 | CMG14: 2594 | CMH14: PWR 60's Choco / Free PT Short (3pcs) | CMI14: 3 | CMJ14: 4050 | CMK14: 2594 | CML14: PWR 60's Choco / Free PT Short (3pcs) | CMM14: 3 | CMN14: 4050 | CMO14: 2594 | CMP14: PWR 60's Choco / Free PT Short (3pcs) | CMQ14: 3 | CMR14: 4050 | CMS14: 2594 | CMT14: PWR 60's Choco / Free PT Short (3pcs) | CMU14: 3 | CMV14: 4050 | CMW14: 2594 | CMX14: PWR 60's Choco / Free PT Short (3pcs) | CMY14: 3 | CMZ14: 4050 | CNA14: 2594 | CNB14: PWR 60's Choco / Free PT Short (3pcs) | CNC14: 3 | CND14: 4050 | CNE14: 2594 | CNF14: PWR 60's Choco / Free PT Short (3pcs) | CNG14: 3 | CNH14: 4050 | CNI14: 2594 | CNJ14: PWR 60's Choco / Free PT Short (3pcs) | CNK14: 3 | CNL14: 4050 | CNM14: 2594 | CNN14: PWR 60's Choco / Free PT Short (3pcs) | CNO14: 3 | CNP14: 4050 | CNQ14: 2594 | CNR14: PWR 60's Choco / Free PT Short (3pcs) | CNS14: 3 | CNT14: 4050 | CNU14: 2594 | CNV14: PWR 60's Choco / Free PT Short (3pcs) | CNW14: 3 | CNX14: 4050 | CNY14: 2594 | CNZ14: PWR 60's Choco / Free PT Short (3pcs) | COA14: 3 | COB14: 4050 | COC14: 2594 | COD14: PWR 60's Choco / Free PT Short (3pcs) | COE14: 3 | COF14: 4050 | COG14: 2594 | COH14: PWR 60's Choco / Free PT Short (3pcs) | COI14: 3 | COJ14: 4050 | COK14: 2594 | COL14: PWR 60's Choco / Free PT Short (3pcs) | COM14: 3 | CON14: 4050 | COO14: 2594 | COP14: PWR 60's Choco / Free PT Short (3pcs) | COQ14: 3 | COR14: 4050 | COS14: 2594 | COT14: PWR 60's Choco / Free PT Short (3pcs) | COU14: 3 | COV14: 4050 | COW14: 2594 | COX14: PWR 60's Choco / Free PT Short (3pcs) | COY14: 3 | COZ14: 4050 | CPA14: 2594 | CPB14: PWR 60's Choco / Free PT Short (3pcs) | CPC14: 3 | CPD14: 4050 | CPE14: 2594 | CPF14: PWR 60's Choco / Free PT Short (3pcs) | CPG14: 3 | CPH14: 4050 | CPI14: 2594 | CPJ14: PWR 60's Choco / Free PT Short (3pcs) | CPK14: 3 | CPL14: 4050 | CPM14: 2594 | CPN14: PWR 60's Choco / Free PT Short (3pcs) | CPO14: 3 | CPP14: 4050 | CPQ14: 2594 | CPR14: PWR 60's Choco / Free PT Short (3pcs) | CPS14: 3 | CPT14: 4050 | CPU14: 2594 | CPV14: PWR 60's Choco / Free PT Short (3pcs) | CPW14: 3 | CPX14: 4050 | CPY14: 2594 | CPZ14: PWR 60's Choco / Free PT Short (3pcs) | CQA14: 3 | CQB14: 4050 | CQC14: 2594 | CQD14: PWR 60's Choco / Free PT Short (3pcs) | CQE14: 3 | CQF14: 4050 | CQG14: 2594 | CQH14: PWR 60's Choco / Free PT Short (3pcs) | CQI14: 3 | CQJ14: 4050 | CQK14: 2594 | CQL14: PWR 60's Choco / Free PT Short (3pcs) | CQM14: 3 | CQN14: 4050 | CQO14: 2594 | CQP14: PWR 60's Choco / Free PT Short (3pcs) | CQQ14: 3 | CQR14: 4050 | CQS14: 2594 | CQT14: PWR 60's Choco / Free PT Short (3pcs) | CQU14: 3 | CQV14: 4050 | CQW14: 2594 | CQX14: PWR 60's Choco / Free PT Short (3pcs) | CQY14: 3 | CQZ14: 4050 | CRA14: 2594 | CRB14: PWR 60's Choco / Free PT Short (3pcs) | CRC14: 3 | CRD14: 4050 | CRE14: 2594 | CRF14: PWR 60's Choco / Free PT Short (3pcs) | CRG14: 3 | CRH14: 4050 | CRI14: 2594 | CRJ14: PWR 60's Choco / Free PT Short (3pcs) | CRK14: 3 | CRL14: 4050 | CRM14: 2594 | CRN14: PWR 60's Choco / Free PT Short (3pcs) | CRO14: 3 | CRP14: 4050 | CRQ14: 2594 | CRR14: PWR 60's Choco / Free PT Short (3pcs) | CRS14: 3 | CRT14: 4050 | CRU14: 2594 | CRV14: PWR 60's Choco / Free PT Short (3pcs) | CRW14: 3 | CRX14: 4050 | CRY14: 2594 | CRZ14: PWR 60's Choco / Free PT Short (3pcs) | CSA14: 3 | CSB14: 4050 | CSC14: 2594 | CSD14: PWR 60's Choco / Free PT Short (3pcs) | CSE14: 3 | CSF14: 4050 | CSG14: 2594 | CSH14: PWR 60's Choco / Free PT Short (3pcs) | CSI14: 3 | CSJ14: 4050 | CSK14: 2594 | CSL14: PWR 60's Choco / Free PT Short (3pcs) | CSM14: 3 | CSN14: 4050 | CSO14: 2594 | CSP14: PWR 60's Choco / Free PT Short (3pcs) | CSQ14: 3 | CSR14: 4050 | CSS14: 2594 | CST14: PWR 60's Choco / Free PT Short (3pcs) | CSU14: 3 | CSV14: 4050 | CSW14: 2594 | CSX14: PWR 60's Choco / Free PT Short (3pcs) | CSY14: 3 | CSZ14: 4050 | CTA14: 2594 | CTB14: PWR 60's Choco / Free PT Short (3pcs) | CTC14: 3 | CTD14: 4050 | CTE14: 2594 | CTF14: PWR 60's Choco / Free PT Short (3pcs) | CTG14: 3 | CTH14: 4050 | CTI14: 2594 | CTJ14: PWR 60's Choco / Free PT Short (3pcs) | CTK14: 3 | CTL14: 4050 | CTM14: 2594 | CTN14: PWR 60's Choco / Free PT Short (3pcs) | CTO14: 3 | CTP14: 4050 | CTQ14: 2594 | CTR14: PWR 60's Choco / Free PT Short (3pcs) | CTS14: 3 | CTT14: 4050 | CTU14: 2594 | CTV14: PWR 60's Choco / Free PT Short (3pcs) | CTW14: 3 | CTX14: 4050 | CTY14: 2594 | CTZ14: PWR 60's Choco / Free PT Short (3pcs) | CUA14: 3 | CUB14: 4050 | CUC14: 2594 | CUD14: PWR 60's Choco / Free PT Short (3pcs) | CUE14: 3 | CUF14: 4050 | CUG14: 2594 | CUH14: PWR 60's Choco / Free PT Short (3pcs) | CUI14: 3 | CUJ14: 4050 | CUK14: 2594 | CUL14: PWR 60's Choco / Free PT Short (3pcs) | CUM14: 3 | CUN14: 4050 | CUO14: 2594 | CUP14: PWR 60's Choco / Free PT Short (3pcs) | CUQ14: 3 | CUR14: 4050 | CUS14: 2594 | CUT14: PWR 60's Choco / Free PT Short (3pcs) | CUU14: 3 | CUV14: 4050 | CUW14: 2594 | CUX14: PWR 60's Choco / Free PT Short (3pcs) | CUY14: 3 | CUZ14: 4050 | CVA14: 2594 | CVB14: PWR 60's Choco / Free PT Short (3pcs) | CVC14: 3 | CVD14: 4050 | CVE14: 2594 | CVF14: PWR 60's Choco / Free PT Short (3pcs) | CVG14: 3 | CVH14: 4050 | CVI14: 2594 | CVJ14: PWR 60's Choco / Free PT Short (3pcs) | CVK14: 3 | CVL14: 4050 | CVM14: 2594 | CVN14: PWR 60's Choco / Free PT Short (3pcs) | CVO14: 3 | CVP14: 4050 | CVQ14: 2594 | CVR14: PWR 60's Choco / Free PT Short (3pcs) | CVS14: 3 | CVT14: 4050 | CVU14: 2594 | CVV14: PWR 60's Choco / Free PT Short (3pcs) | CVW14: 3 | CVX14: 4050 | CVY14: 2594 | CVZ14: PWR 60's Choco / Free PT Short (3pcs) | CWA14: 3 | CWB14: 4050 | CWC14: 2594 | CWD14: PWR 60's Choco / Free PT Short (3pcs) | CWE14: 3 | CWF14: 4050 | CWG14: 2594 | CWH14: PWR 60's Choco / Free PT Short (3pcs) | CWI14: 3 | CWJ14: 4050 | CWK14: 2594 | CWL14: PWR 60's Choco / Free PT Short (3pcs) | CWM14: 3 | CWN14: 4050 | CWO14: 2594 | CWP14: PWR 60's Choco / Free PT Short (3pcs) | CWQ14: 3 | CWR14: 4050 | CWS14: 2594 | CWT14: PWR 60's Choco / Free PT Short (3pcs) | CWU14: 3 | CWV14: 4050 | CWW14: 2594 | CWX14: PWR 60's Choco / Free PT Short (3pcs) | CWY14: 3 | CWZ14: 4050 | CXA14: 2594 | CXB14: PWR 60's Choco / Free PT Short (3pcs) | CXC14: 3 | CXD14: 4050 | CXE14: 2594 | CXF14: PWR 60's Choco / Free PT Short (3pcs) | CXG14: 3 | CXH14: 4050 | CXI14: 2594 | CXJ14: PWR 60's Choco / Free PT Short (3pcs) | CXK14: 3 | CXL14: 4050 | CXM14: 2594 | CXN14: PWR 60's Choco / Free PT Short (3pcs) | CXO14: 3 | CXP14: 4050 | CXQ14: 2594 | CXR14: PWR 60's Choco / Free PT Short (3pcs) | CXS14: 3 | CXT14: 4050 | CXU14: 2594 | CXV14: PWR 60's Choco / Free PT Short (3pcs) | CXW14: 3 | CXX14: 4050 | CXY14: 2594 | CXZ14: PWR 60's Choco / Free PT Short (3pcs) | CYA14: 3 | CYB14: 4050 | CYC14: 2594 | CYD14: PWR 60's Choco / Free PT Short (3pcs) | CYE14: 3 | CYF14: 4050 | CYG14: 2594 | CYH14: PWR 60's Choco / Free PT Short (3pcs) | CYI14: 3 | CYJ14: 4050 | CYK14: 2594 | CYL14: PWR 60's Choco / Free PT Short (3pcs) | CYM14: 3 | CYN14: 4050 | CYO14: 2594 | CYP14: PWR 60's Choco / Free PT Short (3pcs) | CYQ14: 3 | CYR14: 4050 | CYS14: 2594 | CYT14: PWR 60's Choco / Free PT Short (3pcs) | CYU14: 3 | CYV14: 4050 | CYW14: 2594 | CYX14: PWR 60's Choco / Free PT Short (3pcs) | CYY14: 3 | CYZ14: 4050 | CZA14: 2594 | CZB14: PWR 60's Choco / Free PT Short (3pcs) | CZC14: 3 | CZD14: 4050 | CZE14: 2594 | CZF14: PWR 60's Choco / Free PT Short (3pcs) | CZG14: 3 | CZH14: 4050 | CZI14: 2594 | CZJ14: PWR 60's Choco / Free PT Short (3pcs) | CZK14: 3 | CZL14: 4050 | CZM14: 2594 | CZN14: PWR 60's Choco / Free PT Short (3pcs) | CZO14: 3 | CZP14: 4050 | CZQ14: 2594 | CZR14: PWR 60's Choco / Free PT Short (3pcs) | CZS14: 3 | CZT14: 4050 | CZU14: 2594 | CZV14: PWR 60's Choco / Free PT Short (3pcs) | CZW14: 3 | CZX14: 4050 | CZY14: 2594 | CZZ14: PWR 60's Choco / Free PT Short (3pcs) | DAA14: 3 | DAB14: 4050 | DAC14: 2594 | DAD14: PWR 60's Choco / Free PT Short (3pcs) | DAE14: 3 | DAF14: 4050 | DAG14: 2594 | DAH14: PWR 60's Choco / Free PT Short (3pcs) | DAI14: 3 | DAJ14: 4050 | DAK14: 2594 | DAL14: PWR 60's Choco / Free PT Short (3pcs) | DAM14: 3 | DAN14: 4050 | DAO14: 2594 | DAP14: PWR 60's Choco / Free PT Short (3pcs) | DAQ14: 3 | DAR14: 4050 | DAS14: 2594 | DAT14: PWR 60's Choco / Free PT Short (3pcs) | DAU14: 3 | DAV14: 4050 | DAW14: 2594 | DAX14: PWR 60's Choco / Free PT Short (3pcs) | DAY14: 3 | DAZ14: 4050 | DBA14: 2594 | DBB14: PWR 60's Choco / Free PT Short (3pcs) | DBC14: 3 | DBD14: 4050 | DBE14: 2594 | DBF14: PWR 60's Choco / Free PT Short (3pcs) | DBG14: 3 | DBH14: 4050 | DBI14: 2594 | DBJ14: PWR 60's Choco / Free PT Short (3pcs) | DBK14: 3 | DBL14: 4050 | DBM14: 2594 | DBN14: PWR 60's Choco / Free PT Short (3pcs) | DBO14: 3 | DBP14: 4050 | DBQ14: 2594 | DBR14: PWR 60's Choco / Free PT Short (3pcs) | DBS14: 3 | DBT14: 4050 | DBU14: 2594 | DBV14: PWR 60's Choco / Free PT Short (3pcs) | DBW14: 3 | DBX14: 4050 | DBY14: 2594 | DBZ14: PWR 60's Choco / Free PT Short (3pcs) | DCA14: 3 | DCB14: 4050 | DCC14: 2594 | DCD14: PWR 60's Choco / Free PT Short (3pcs) | DCE14: 3 | DCF14: 4050 | DCG14: 2594 | DCH14: PWR 60's Choco / Free PT Short (3pcs) | DCI14: 3 | DCJ14: 4050
A15: 15248 | B15: Muscle Tech Mass Extreme 6lbs | C15: 1 | D15: 2100 | F15: 2100 | G15: ONLINE | DH15: 0 | DJ15: GWS PLASTIC XL | DK15: 2 | DL15: 0 | DN15: GWS PLASTIC XL | DO15: 2 | DP15: 0 | DR15: GWS PLASTIC XL | DS15: 2 | DT15: 0 | DV15: GWS PLASTIC XL | DW15: 2 | DX15: 0 | DZ15: GWS PLASTIC XL | EA15: 2 | EB15: 0 | ED15: GWS PLASTIC XL | EE15: 2 | EF15: 0 | EH15: GWS PLASTIC XL | EI15: 2 | EJ15: 0 | EL15: GWS PLASTIC XL | EM15: 2 | EN15: 0 | EP15: GWS PLASTIC XL | EQ15: 2 | ER15: 0 | ET15: GWS PLASTIC XL | EU15: 2 | EV15: 0 | EX15: GWS PLASTIC XL | EY15: 2 | EZ15: 0 | FB15: GWS PLASTIC XL | FC15: 2 | FD15: 0 | FF15: GWS PLASTIC XL | FG15: 2 | FH15: 0 | FJ15: GWS PLASTIC XL | FK15: 2 | FL15: 0 | FN15: GWS PLASTIC XL | FO15: 2 | FP15: 0 | FR15: GWS PLASTIC XL | FS15: 2 | FT15: 0 | FV15: GWS PLASTIC XL | FW15: 2 | FX15: 0 | FZ15: GWS PLASTIC XL | GA15: 2 | GB15: 0 | GD15: GWS PLASTIC XL | GE15: 2 | GF15: 0 | GH15: GWS PLASTIC XL | GI15: 2 | GJ15: 0 | GL15: GWS PLASTIC XL | GM15: 2 | GN15: 0 | GP15: GWS PLASTIC XL | GQ15: 2 | GR15: 0 | GT15: GWS PLASTIC XL | GU15: 2 | GV15: 0 | GX15: GWS PLASTIC XL | GY15: 2 | GZ15: 0 | HB15: GWS PLASTIC XL | HC15: 2 | HD15: 0 | HF15: GWS PLASTIC XL | HG15: 2 | HH15: 0 | HJ15: GWS PLASTIC XL | HK15: 2 | HL15: 0 | HN15: GWS PLASTIC XL | HO15: 2 | HP15: 0 | HR15: GWS PLASTIC XL | HS15: 2 | HT15: 0 | HV15: GWS PLASTIC XL | HW15: 2 | HX15: 0 | HZ15: GWS PLASTIC XL | IA15: 2 | IB15: 0 | ID15: GWS PLASTIC XL | IE15: 2 | IF15: 0 | IH15: GWS PLASTIC XL | II15: 2 | IJ15: 0 | IL15: GWS PLASTIC XL | IM15: 2 | IN15: 0 | IP15: GWS PLASTIC XL | IQ15: 2 | IR15: 0 | IT15: GWS PLASTIC XL | IU15: 2 | IV15: 0 | IX15: GWS PLASTIC XL | IY15: 2 | IZ15: 0 | JB15: GWS PLASTIC XL | JC15: 2 | JD15: 0 | JF15: GWS PLASTIC XL | JG15: 2 | JH15: 0 | JJ15: GWS PLASTIC XL | JK15: 2 | JL15: 0 | JN15: GWS PLASTIC XL | JO15: 2 | JP15: 0 | JR15: GWS PLASTIC XL | JS15: 2 | JT15: 0 | JV15: GWS PLASTIC XL | JW15: 2 | JX15: 0 | JZ15: GWS PLASTIC XL | KA15: 2 | KB15: 0 | KD15: GWS PLASTIC XL | KE15: 2 | KF15: 0 | KH15: GWS PLASTIC XL | KI15: 2 | KJ15: 0 | KL15: GWS PLASTIC XL | KM15: 2 | KN15: 0 | KP15: GWS PLASTIC XL | KQ15: 2 | KR15: 0 | KT15: GWS PLASTIC XL | KU15: 2 | KV15: 0 | KX15: GWS PLASTIC XL | KY15: 2 | KZ15: 0 | LB15: GWS PLASTIC XL | LC15: 2 | LD15: 0 | LF15: GWS PLASTIC XL | LG15: 2 | LH15: 0 | LJ15: GWS PLASTIC XL | LK15: 2 | LL15: 0 | LN15: GWS PLASTIC XL | LO15: 2 | LP15: 0 | LR15: GWS PLASTIC XL | LS15: 2 | LT15: 0 | LV15: GWS PLASTIC XL | LW15: 2 | LX15: 0 | LZ15: GWS PLASTIC XL | MA15: 2 | MB15: 0 | MD15: GWS PLASTIC XL | ME15: 2 | MF15: 0 | MH15: GWS PLASTIC XL | MI15: 2 | MJ15: 0 | ML15: GWS PLASTIC XL | MM15: 2 | MN15: 0 | MP15: GWS PLASTIC XL | MQ15: 2 | MR15: 0 | MT15: GWS PLASTIC XL | MU15: 2 | MV15: 0 | MX15: GWS PLASTIC XL | MY15: 2 | MZ15: 0 | NB15: GWS PLASTIC XL | NC15: 2 | ND15: 0 | NF15: GWS PLASTIC XL | NG15: 2 | NH15: 0 | NJ15: GWS PLASTIC XL | NK15: 2 | NL15: 0 | NN15: GWS PLASTIC XL | NO15: 2 | NP15: 0 | NR15: GWS PLASTIC XL | NS15: 2 | NT15: 0 | NV15: GWS PLASTIC XL | NW15: 2 | NX15: 0 | NZ15: GWS PLASTIC XL | OA15: 2 | OB15: 0 | OD15: GWS PLASTIC XL | OE15: 2 | OF15: 0 | OH15: GWS PLASTIC XL | OI15: 2 | OJ15: 0 | OL15: GWS PLASTIC XL | OM15: 2 | ON15: 0 | OP15: GWS PLASTIC XL | OQ15: 2 | OR15: 0 | OT15: GWS PLASTIC XL | OU15: 2 | OV15: 0 | OX15: GWS PLASTIC XL | OY15: 2 | OZ15: 0 | PB15: GWS PLASTIC XL | PC15: 2 | PD15: 0 | PF15: GWS PLASTIC XL | PG15: 2 | PH15: 0 | PJ15: GWS PLASTIC XL | PK15: 2 | PL15: 0 | PN15: GWS PLASTIC XL | PO15: 2 | PP15: 0 | PR15: GWS PLASTIC XL | PS15: 2 | PT15: 0 | PV15: GWS PLASTIC XL | PW15: 2 | PX15: 0 | PZ15: GWS PLASTIC XL | QA15: 2 | QB15: 0 | QD15: GWS PLASTIC XL | QE15: 2 | QF15: 0 | QH15: GWS PLASTIC XL | QI15: 2 | QJ15: 0 | QL15: GWS PLASTIC XL | QM15: 2 | QN15: 0 | QP15: GWS PLASTIC XL | QQ15: 2 | QR15: 0 | QT15: GWS PLASTIC XL | QU15: 2 | QV15: 0 | QX15: GWS PLASTIC XL | QY15: 2 | QZ15: 0 | RB15: GWS PLASTIC XL | RC15: 2 | RD15: 0 | RF15: GWS PLASTIC XL | RG15: 2 | RH15: 0 | RJ15: GWS PLASTIC XL | RK15: 2 | RL15: 0 | RN15: GWS PLASTIC XL | RO15: 2 | RP15: 0 | RR15: GWS PLASTIC XL | RS15: 2 | RT15: 0 | RV15: GWS PLASTIC XL | RW15: 2 | RX15: 0 | RZ15: GWS PLASTIC XL | SA15: 2 | SB15: 0 | SD15: GWS PLASTIC XL | SE15: 2 | SF15: 0 | SH15: GWS PLASTIC XL | SI15: 2 | SJ15: 0 | SL15: GWS PLASTIC XL | SM15: 2 | SN15: 0 | SP15: GWS PLASTIC XL | SQ15: 2 | SR15: 0 | ST15: GWS PLASTIC XL | SU15: 2 | SV15: 0 | SX15: GWS PLASTIC XL | SY15: 2 | SZ15: 0 | TB15: GWS PLASTIC XL | TC15: 2 | TD15: 0 | TF15: GWS PLASTIC XL | TG15: 2 | TH15: 0 | TJ15: GWS PLASTIC XL | TK15: 2 | TL15: 0 | TN15: GWS PLASTIC XL | TO15: 2 | TP15: 0 | TR15: GWS PLASTIC XL | TS15: 2 | TT15: 0 | TV15: GWS PLASTIC XL | TW15: 2 | TX15: 0 | TZ15: GWS PLASTIC XL | UA15: 2 | UB15: 0 | UD15: GWS PLASTIC XL | UE15: 2 | UF15: 0 | UH15: GWS PLASTIC XL | UI15: 2 | UJ15: 0 | UL15: GWS PLASTIC XL | UM15: 2 | UN15: 0 | UP15: GWS PLASTIC XL | UQ15: 2 | UR15: 0 | UT15: GWS PLASTIC XL | UU15: 2 | UV15: 0 | UX15: GWS PLASTIC XL | UY15: 2 | UZ15: 0 | VB15: GWS PLASTIC XL | VC15: 2 | VD15: 0 | VF15: GWS PLASTIC XL | VG15: 2 | VH15: 0 | VJ15: GWS PLASTIC XL | VK15: 2 | VL15: 0 | VN15: GWS PLASTIC XL | VO15: 2 | VP15: 0 | VR15: GWS PLASTIC XL | VS15: 2 | VT15: 0 | VV15: GWS PLASTIC XL | VW15: 2 | VX15: 0 | VZ15: GWS PLASTIC XL | WA15: 2 | WB15: 0 | WD15: GWS PLASTIC XL | WE15: 2 | WF15: 0 | WH15: GWS PLASTIC XL | WI15: 2 | WJ15: 0 | WL15: GWS PLASTIC XL | WM15: 2 | WN15: 0 | WP15: GWS PLASTIC XL | WQ15: 2 | WR15: 0 | WT15: GWS PLASTIC XL | WU15: 2 | WV15: 0 | WX15: GWS PLASTIC XL | WY15: 2 | WZ15: 0 | XB15: GWS PLASTIC XL | XC15: 2 | XD15: 0 | XF15: GWS PLASTIC XL | XG15: 2 | XH15: 0 | XJ15: GWS PLASTIC XL | XK15: 2 | XL15: 0 | XN15: GWS PLASTIC XL | XO15: 2 | XP15: 0 | XR15: GWS PLASTIC XL | XS15: 2 | XT15: 0 | XV15: GWS PLASTIC XL | XW15: 2 | XX15: 0 | XZ15: GWS PLASTIC XL | YA15: 2 | YB15: 0 | YD15: GWS PLASTIC XL | YE15: 2 | YF15: 0 | YH15: GWS PLASTIC XL | YI15: 2 | YJ15: 0 | YL15: GWS PLASTIC XL | YM15: 2 | YN15: 0 | YP15: GWS PLASTIC XL | YQ15: 2 | YR15: 0 | YT15: GWS PLASTIC XL | YU15: 2 | YV15: 0 | YX15: GWS PLASTIC XL | YY15: 2 | YZ15: 0 | ZB15: GWS PLASTIC XL | ZC15: 2 | ZD15: 0 | ZF15: GWS PLASTIC XL | ZG15: 2 | ZH15: 0 | ZJ15: GWS PLASTIC XL | ZK15: 2 | ZL15: 0 | ZN15: GWS PLASTIC XL | ZO15: 2 | ZP15: 0 | ZR15: GWS PLASTIC XL | ZS15: 2 | ZT15: 0 | ZV15: GWS PLASTIC XL | ZW15: 2 | ZX15: 0 | ZZ15: GWS PLASTIC XL | AAA15: 2 | AAB15: 0 | AAD15: GWS PLASTIC XL | AAE15: 2 | AAF15: 0 | AAH15: GWS PLASTIC XL | AAI15: 2 | AAJ15: 0 | AAL15: GWS PLASTIC XL | AAM15: 2 | AAN15: 0 | AAP15: GWS PLASTIC XL | AAQ15: 2 | AAR15: 0 | AAT15: GWS PLASTIC XL | AAU15: 2 | AAV15: 0 | AAX15: GWS PLASTIC XL | AAY15: 2 | AAZ15: 0 | ABB15: GWS PLASTIC XL | ABC15: 2 | ABD15: 0 | ABF15: GWS PLASTIC XL | ABG15: 2 | ABH15: 0 | ABJ15: GWS PLASTIC XL | ABK15: 2 | ABL15: 0 | ABN15: GWS PLASTIC XL | ABO15: 2 | ABP15: 0 | ABR15: GWS PLASTIC XL | ABS15: 2 | ABT15: 0 | ABV15: GWS PLASTIC XL | ABW15: 2 | ABX15: 0 | ABZ15: GWS PLASTIC XL | ACA15: 2 | ACB15: 0 | ACD15: GWS PLASTIC XL | ACE15: 2 | ACF15: 0 | ACH15: GWS PLASTIC XL | ACI15: 2 | ACJ15: 0 | ACL15: GWS PLASTIC XL | ACM15: 2 | ACN15: 0 | ACP15: GWS PLASTIC XL | ACQ15: 2 | ACR15: 0 | ACT15: GWS PLASTIC XL | ACU15: 2 | ACV15: 0 | ACX15: GWS PLASTIC XL | ACY15: 2 | ACZ15: 0 | ADB15: GWS PLASTIC XL | ADC15: 2 | ADD15: 0 | ADF15: GWS PLASTIC XL | ADG15: 2 | ADH15: 0 | ADJ15: GWS PLASTIC XL | ADK15: 2 | ADL15: 0 | ADN15: GWS PLASTIC XL | ADO15: 2 | ADP15: 0 | ADR15: GWS PLASTIC XL | ADS15: 2 | ADT15: 0 | ADV15: GWS PLASTIC XL | ADW15: 2 | ADX15: 0 | ADZ15: GWS PLASTIC XL | AEA15: 2 | AEB15: 0 | AED15: GWS PLASTIC XL | AEE15: 2 | AEF15: 0 | AEH15: GWS PLASTIC XL | AEI15: 2 | AEJ15: 0 | AEL15: GWS PLASTIC XL | AEM15: 2 | AEN15: 0 | AEP15: GWS PLASTIC XL | AEQ15: 2 | AER15: 0 | AET15: GWS PLASTIC XL | AEU15: 2 | AEV15: 0 | AEX15: GWS PLASTIC XL | AEY15: 2 | AEZ15: 0 | AFB15: GWS PLASTIC XL | AFC15: 2 | AFD15: 0 | AFF15: GWS PLASTIC XL | AFG15: 2 | AFH15: 0 | AFJ15: GWS PLASTIC XL | AFK15: 2 | AFL15: 0 | AFN15: GWS PLASTIC XL | AFO15: 2 | AFP15: 0 | AFR15: GWS PLASTIC XL | AFS15: 2 | AFT15: 0 | AFV15: GWS PLASTIC XL | AFW15: 2 | AFX15: 0 | AFZ15: GWS PLASTIC XL | AGA15: 2 | AGB15: 0 | AGD15: GWS PLASTIC XL | AGE15: 2 | AGF15: 0 | AGH15: GWS PLASTIC XL | AGI15: 2 | AGJ15: 0 | AGL15: GWS PLASTIC XL | AGM15: 2 | AGN15: 0 | AGP15: GWS PLASTIC XL | AGQ15: 2 | AGR15: 0 | AGT15: GWS PLASTIC XL | AGU15: 2 | AGV15: 0 | AGX15: GWS PLASTIC XL | AGY15: 2 | AGZ15: 0 | AHB15: GWS PLASTIC XL | AHC15: 2 | AHD15: 0 | AHF15: GWS PLASTIC XL | AHG15: 2 | AHH15: 0 | AHJ15: GWS PLASTIC XL | AHK15: 2 | AHL15: 0 | AHN15: GWS PLASTIC XL | AHO15: 2 | AHP15: 0 | AHR15: GWS PLASTIC XL | AHS15: 2 | AHT15: 0 | AHV15: GWS PLASTIC XL | AHW15: 2 | AHX15: 0 | AHZ15: GWS PLASTIC XL | AIA15: 2 | AIB15: 0 | AID15: GWS PLASTIC XL | AIE15: 2 | AIF15: 0 | AIH15: GWS PLASTIC XL | AII15: 2 | AIJ15: 0 | AIL15: GWS PLASTIC XL | AIM15: 2 | AIN15: 0 | AIP15: GWS PLASTIC XL | AIQ15: 2 | AIR15: 0 | AIT15: GWS PLASTIC XL | AIU15: 2 | AIV15: 0 | AIX15: GWS PLASTIC XL | AIY15: 2 | AIZ15: 0 | AJB15: GWS PLASTIC XL | AJC15: 2 | AJD15: 0 | AJF15: GWS PLASTIC XL | AJG15: 2 | AJH15: 0 | AJJ15: GWS PLASTIC XL | AJK15: 2 | AJL15: 0 | AJN15: GWS PLASTIC XL | AJO15: 2 | AJP15: 0 | AJR15: GWS PLASTIC XL | AJS15: 2 | AJT15: 0 | AJV15: GWS PLASTIC XL | AJW15: 2 | AJX15: 0 | AJZ15: GWS PLASTIC XL | AKA15: 2 | AKB15: 0 | AKD15: GWS PLASTIC XL | AKE15: 2 | AKF15: 0 | AKH15: GWS PLASTIC XL | AKI15: 2 | AKJ15: 0 | AKL15: GWS PLASTIC XL | AKM15: 2 | AKN15: 0 | AKP15: GWS PLASTIC XL | AKQ15: 2 | AKR15: 0 | AKT15: GWS PLASTIC XL | AKU15: 2 | AKV15: 0 | AKX15: GWS PLASTIC XL | AKY15: 2 | AKZ15: 0 | ALB15: GWS PLASTIC XL | ALC15: 2 | ALD15: 0 | ALF15: GWS PLASTIC XL | ALG15: 2 | ALH15: 0 | ALJ15: GWS PLASTIC XL | ALK15: 2 | ALL15: 0 | ALN15: GWS PLASTIC XL | ALO15: 2 | ALP15: 0 | ALR15: GWS PLASTIC XL | ALS15: 2 | ALT15: 0 | ALV15: GWS PLASTIC XL | ALW15: 2 | ALX15: 0 | ALZ15: GWS PLASTIC XL | AMA15: 2 | AMB15: 0 | AMD15: GWS PLASTIC XL | AME15: 2 | AMF15: 0 | AMH15: GWS PLASTIC XL | AMI15: 2 | AMJ15: 0 | AML15: GWS PLASTIC XL | AMM15: 2 | AMN15: 0 | AMP15: GWS PLASTIC XL | AMQ15: 2 | AMR15: 0 | AMT15: GWS PLASTIC XL | AMU15: 2 | AMV15: 0 | AMX15: GWS PLASTIC XL | AMY15: 2 | AMZ15: 0 | ANB15: GWS PLASTIC XL | ANC15: 2 | AND15: 0 | ANF15: GWS PLASTIC XL | ANG15: 2 | ANH15: 0 | ANJ15: GWS PLASTIC XL | ANK15: 2 | ANL15: 0 | ANN15: GWS PLASTIC XL | ANO15: 2 | ANP15: 0 | ANR15: GWS PLASTIC XL | ANS15: 2 | ANT15: 0 | ANV15: GWS PLASTIC XL | ANW15: 2 | ANX15: 0 | ANZ15: GWS PLASTIC XL | AOA15: 2 | AOB15: 0 | AOD15: GWS PLASTIC XL | AOE15: 2 | AOF15: 0 | AOH15: GWS PLASTIC XL | AOI15: 2 | AOJ15: 0 | AOL15: GWS PLASTIC XL | AOM15: 2 | AON15: 0 | AOP15: GWS PLASTIC XL | AOQ15: 2 | AOR15: 0 | AOT15: GWS PLASTIC XL | AOU15: 2 | AOV15: 0 | AOX15: GWS PLASTIC XL | AOY15: 2 | AOZ15: 0 | APB15: GWS PLASTIC XL | APC15: 2 | APD15: 0 | APF15: GWS PLASTIC XL | APG15: 2 | APH15: 0 | APJ15: GWS PLASTIC XL | APK15: 2 | APL15: 0 | APN15: GWS PLASTIC XL | APO15: 2 | APP15: 0 | APR15: GWS PLASTIC XL | APS15: 2 | APT15: 0 | APV15: GWS PLASTIC XL | APW15: 2 | APX15: 0 | APZ15: GWS PLASTIC XL | AQA15: 2 | AQB15: 0 | AQD15: GWS PLASTIC XL | AQE15: 2 | AQF15: 0 | AQH15: GWS PLASTIC XL | AQI15: 2 | AQJ15: 0 | AQL15: GWS PLASTIC XL | AQM15: 2 | AQN15: 0 | AQP15: GWS PLASTIC XL | AQQ15: 2 | AQR15: 0 | AQT15: GWS PLASTIC XL | AQU15: 2 | AQV15: 0 | AQX15: GWS PLASTIC XL | AQY15: 2 | AQZ15: 0 | ARB15: GWS PLASTIC XL | ARC15: 2 | ARD15: 0 | ARF15: GWS PLASTIC XL | ARG15: 2 | ARH15: 0 | ARJ15: GWS PLASTIC XL | ARK15: 2 | ARL15: 0 | ARN15: GWS PLASTIC XL | ARO15: 2 | ARP15: 0 | ARR15: GWS PLASTIC XL | ARS15: 2 | ART15: 0 | ARV15: GWS PLASTIC XL | ARW15: 2 | ARX15: 0 | ARZ15: GWS PLASTIC XL | ASA15: 2 | ASB15: 0 | ASD15: GWS PLASTIC XL | ASE15: 2 | ASF15: 0 | ASH15: GWS PLASTIC XL | ASI15: 2 | ASJ15: 0 | ASL15: GWS PLASTIC XL | ASM15: 2 | ASN15: 0 | ASP15: GWS PLASTIC XL | ASQ15: 2 | ASR15: 0 | AST15: GWS PLASTIC XL | ASU15: 2 | ASV15: 0 | ASX15: GWS PLASTIC XL | ASY15: 2 | ASZ15: 0 | ATB15: GWS PLASTIC XL | ATC15: 2 | ATD15: 0 | ATF15: GWS PLASTIC XL | ATG15: 2 | ATH15: 0 | ATJ15: GWS PLASTIC XL | ATK15: 2 | ATL15: 0 | ATN15: GWS PLASTIC XL | ATO15: 2 | ATP15: 0 | ATR15: GWS PLASTIC XL | ATS15: 2 | ATT15: 0 | ATV15: GWS PLASTIC XL | ATW15: 2 | ATX15: 0 | ATZ15: GWS PLASTIC XL | AUA15: 2 | AUB15: 0 | AUD15: GWS PLASTIC XL | AUE15: 2 | AUF15: 0 | AUH15: GWS PLASTIC XL | AUI15: 2 | AUJ15: 0 | AUL15: GWS PLASTIC XL | AUM15: 2 | AUN15: 0 | AUP15: GWS PLASTIC XL | AUQ15: 2 | AUR15: 0 | AUT15: GWS PLASTIC XL | AUU15: 2 | AUV15: 0 | AUX15: GWS PLASTIC XL | AUY15: 2 | AUZ15: 0 | AVB15: GWS PLASTIC XL | AVC15: 2 | AVD15: 0 | AVF15: GWS PLASTIC XL | AVG15: 2 | AVH15: 0 | AVJ15: GWS PLASTIC XL | AVK15: 2 | AVL15: 0 | AVN15: GWS PLASTIC XL | AVO15: 2 | AVP15: 0 | AVR15: GWS PLASTIC XL | AVS15: 2 | AVT15: 0 | AVV15: GWS PLASTIC XL | AVW15: 2 | AVX15: 0 | AVZ15: GWS PLASTIC XL | AWA15: 2 | AWB15: 0 | AWD15: GWS PLASTIC XL | AWE15: 2 | AWF15: 0 | AWH15: GWS PLASTIC XL | AWI15: 2 | AWJ15: 0 | AWL15: GWS PLASTIC XL | AWM15: 2 | AWN15: 0 | AWP15: GWS PLASTIC XL | AWQ15: 2 | AWR15: 0 | AWT15: GWS PLASTIC XL | AWU15: 2 | AWV15: 0 | AWX15: GWS PLASTIC XL | AWY15: 2 | AWZ15: 0 | AXB15: GWS PLASTIC XL | AXC15: 2 | AXD15: 0 | AXF15: GWS PLASTIC XL | AXG15: 2 | AXH15: 0 | AXJ15: GWS PLASTIC XL | AXK15: 2 | AXL15: 0 | AXN15: GWS PLASTIC XL | AXO15: 2 | AXP15: 0 | AXR15: GWS PLASTIC XL | AXS15: 2 | AXT15: 0 | AXV15: GWS PLASTIC XL | AXW15: 2 | AXX15: 0 | AXZ15: GWS PLASTIC XL | AYA15: 2 | AYB15: 0 | AYD15: GWS PLASTIC XL | AYE15: 2 | AYF15: 0 | AYH15: GWS PLASTIC XL | AYI15: 2 | AYJ15: 0 | AYL15: GWS PLASTIC XL | AYM15: 2 | AYN15: 0 | AYP15: GWS PLASTIC XL | AYQ15: 2 | AYR15: 0 | AYT15: GWS PLASTIC XL | AYU15: 2 | AYV15: 0 | AYX15: GWS PLASTIC XL | AYY15: 2 | AYZ15: 0 | AZB15: GWS PLASTIC XL | AZC15: 2 | AZD15: 0 | AZF15: GWS PLASTIC XL | AZG15: 2 | AZH15: 0 | AZJ15: GWS PLASTIC XL | AZK15: 2 | AZL15: 0 | AZN15: GWS PLASTIC XL | AZO15: 2 | AZP15: 0 | AZR15: GWS PLASTIC XL | AZS15: 2 | AZT15: 0 | AZV15: GWS PLASTIC XL | AZW15: 2 | AZX15: 0 | AZZ15: GWS PLASTIC XL | BAA15: 2 | BAB15: 0 | BAD15: GWS PLASTIC XL | BAE15: 2 | BAF15: 0 | BAH15: GWS PLASTIC XL | BAI15: 2 | BAJ15: 0 | BAL15: GWS PLASTIC XL | BAM15: 2 | BAN15: 0 | BAP15: GWS PLASTIC XL | BAQ15: 2 | BAR15: 0 | BAT15: GWS PLASTIC XL | BAU15: 2 | BAV15: 0 | BAX15: GWS PLASTIC XL | BAY15: 2 | BAZ15: 0 | BBB15: GWS PLASTIC XL | BBC15: 2 | BBD15: 0 | BBF15: GWS PLASTIC XL | BBG15: 2 | BBH15: 0 | BBJ15: GWS PLASTIC XL | BBK15: 2 | BBL15: 0 | BBN15: GWS PLASTIC XL | BBO15: 2 | BBP15: 0 | BBR15: GWS PLASTIC XL | BBS15: 2 | BBT15: 0 | BBV15: GWS PLASTIC XL | BBW15: 2 | BBX15: 0 | BBZ15: GWS PLASTIC XL | BCA15: 2 | BCB15: 0 | BCD15: GWS PLASTIC XL | BCE15: 2 | BCF15: 0 | BCH15: GWS PLASTIC XL | BCI15: 2 | BCJ15: 0 | BCL15: GWS PLASTIC XL | BCM15: 2 | BCN15: 0 | BCP15: GWS PLASTIC XL | BCQ15: 2 | BCR15: 0 | BCT15: GWS PLASTIC XL | BCU15: 2 | BCV15: 0 | BCX15: GWS PLASTIC XL | BCY15: 2 | BCZ15: 0 | BDB15: GWS PLASTIC XL | BDC15: 2 | BDD15: 0 | BDF15: GWS PLASTIC XL | BDG15: 2 | BDH15: 0 | BDJ15: GWS PLASTIC XL | BDK15: 2 | BDL15: 0 | BDN15: GWS PLASTIC XL | BDO15: 2 | BDP15: 0 | BDR15: GWS PLASTIC XL | BDS15: 2 | BDT15: 0 | BDV15: GWS PLASTIC XL | BDW15: 2 | BDX15: 0 | BDZ15: GWS PLASTIC XL | BEA15: 2 | BEB15: 0 | BED15: GWS PLASTIC XL | BEE15: 2 | BEF15: 0 | BEH15: GWS PLASTIC XL | BEI15: 2 | BEJ15: 0 | BEL15: GWS PLASTIC XL | BEM15: 2 | BEN15: 0 | BEP15: GWS PLASTIC XL | BEQ15: 2 | BER15: 0 | BET15: GWS PLASTIC XL | BEU15: 2 | BEV15: 0 | BEX15: GWS PLASTIC XL | BEY15: 2 | BEZ15: 0 | BFB15: GWS PLASTIC XL | BFC15: 2 | BFD15: 0 | BFF15: GWS PLASTIC XL | BFG15: 2 | BFH15: 0 | BFJ15: GWS PLASTIC XL | BFK15: 2 | BFL15: 0 | BFN15: GWS PLASTIC XL | BFO15: 2 | BFP15: 0 | BFR15: GWS PLASTIC XL | BFS15: 2 | BFT15: 0 | BFV15: GWS PLASTIC XL | BFW15: 2 | BFX15: 0 | BFZ15: GWS PLASTIC XL | BGA15: 2 | BGB15: 0 | BGD15: GWS PLASTIC XL | BGE15: 2 | BGF15: 0 | BGH15: GWS PLASTIC XL | BGI15: 2 | BGJ15: 0 | BGL15: GWS PLASTIC XL | BGM15: 2 | BGN15: 0 | BGP15: GWS PLASTIC XL | BGQ15: 2 | BGR15: 0 | BGT15: GWS PLASTIC XL | BGU15: 2 | BGV15: 0 | BGX15: GWS PLASTIC XL | BGY15: 2 | BGZ15: 0 | BHB15: GWS PLASTIC XL | BHC15: 2 | BHD15: 0 | BHF15: GWS PLASTIC XL | BHG15: 2 | BHH15: 0 | BHJ15: GWS PLASTIC XL | BHK15: 2 | BHL15: 0 | BHN15: GWS PLASTIC XL | BHO15: 2 | BHP15: 0 | BHR15: GWS PLASTIC XL | BHS15: 2 | BHT15: 0 | BHV15: GWS PLASTIC XL | BHW15: 2 | BHX15: 0 | BHZ15: GWS PLASTIC XL | BIA15: 2 | BIB15: 0 | BID15: GWS PLASTIC XL | BIE15: 2 | BIF15: 0 | BIH15: GWS PLASTIC XL | BII15: 2 | BIJ15: 0 | BIL15: GWS PLASTIC XL | BIM15: 2 | BIN15: 0 | BIP15: GWS PLASTIC XL | BIQ15: 2 | BIR15: 0 | BIT15: GWS PLASTIC XL | BIU15: 2 | BIV15: 0 | BIX15: GWS PLASTIC XL | BIY15: 2 | BIZ15: 0 | BJB15: GWS PLASTIC XL | BJC15: 2 | BJD15: 0 | BJF15: GWS PLASTIC XL | BJG15: 2 | BJH15: 0 | BJJ15: GWS PLASTIC XL | BJK15: 2 | BJL15: 0 | BJN15: GWS PLASTIC XL | BJO15: 2 | BJP15: 0 | BJR15: GWS PLASTIC XL | BJS15: 2 | BJT15: 0 | BJV15: GWS PLASTIC XL | BJW15: 2 | BJX15: 0 | BJZ15: GWS PLASTIC XL | BKA15: 2 | BKB15: 0 | BKD15: GWS PLASTIC XL | BKE15: 2 | BKF15: 0 | BKH15: GWS PLASTIC XL | BKI15: 2 | BKJ15: 0 | BKL15: GWS PLASTIC XL | BKM15: 2 | BKN15: 0 | BKP15: GWS PLASTIC XL | BKQ15: 2 | BKR15: 0 | BKT15: GWS PLASTIC XL | BKU15: 2 | BKV15: 0 | BKX15: GWS PLASTIC XL | BKY15: 2 | BKZ15: 0 | BLB15: GWS PLASTIC XL | BLC15: 2 | BLD15: 0 | BLF15: GWS PLASTIC XL | BLG15: 2 | BLH15: 0 | BLJ15: GWS PLASTIC XL | BLK15: 2 | BLL15: 0 | BLN15: GWS PLASTIC XL | BLO15: 2 | BLP15: 0 | BLR15: GWS PLASTIC XL | BLS15: 2 | BLT15: 0 | BLV15: GWS PLASTIC XL | BLW15: 2 | BLX15: 0 | BLZ15: GWS PLASTIC XL | BMA15: 2 | BMB15: 0 | BMD15: GWS PLASTIC XL | BME15: 2 | BMF15: 0 | BMH15: GWS PLASTIC XL | BMI15: 2 | BMJ15: 0 | BML15: GWS PLASTIC XL | BMM15: 2 | BMN15: 0 | BMP15: GWS PLASTIC XL | BMQ15: 2 | BMR15: 0 | BMT15: GWS PLASTIC XL | BMU15: 2 | BMV15: 0 | BMX15: GWS PLASTIC XL | BMY15: 2 | BMZ15: 0 | BNB15: GWS PLASTIC XL | BNC15: 2 | BND15: 0 | BNF15: GWS PLASTIC XL | BNG15: 2 | BNH15: 0 | BNJ15: GWS PLASTIC XL | BNK15: 2 | BNL15: 0 | BNN15: GWS PLASTIC XL | BNO15: 2 | BNP15: 0 | BNR15: GWS PLASTIC XL | BNS15: 2 | BNT15: 0 | BNV15: GWS PLASTIC XL | BNW15: 2 | BNX15: 0 | BNZ15: GWS PLASTIC XL | BOA15: 2 | BOB15: 0 | BOD15: GWS PLASTIC XL | BOE15: 2 | BOF15: 0 | BOH15: GWS PLASTIC XL | BOI15: 2 | BOJ15: 0 | BOL15: GWS PLASTIC XL | BOM15: 2 | BON15: 0 | BOP15: GWS PLASTIC XL | BOQ15: 2 | BOR15: 0 | BOT15: GWS PLASTIC XL | BOU15: 2 | BOV15: 0 | BOX15: GWS PLASTIC XL | BOY15: 2 | BOZ15: 0 | BPB15: GWS PLASTIC XL | BPC15: 2 | BPD15: 0 | BPF15: GWS PLASTIC XL | BPG15: 2 | BPH15: 0 | BPJ15: GWS PLASTIC XL | BPK15: 2 | BPL15: 0 | BPN15: GWS PLASTIC XL | BPO15: 2 | BPP15: 0 | BPR15: GWS PLASTIC XL | BPS15: 2 | BPT15: 0 | BPV15: GWS PLASTIC XL | BPW15: 2 | BPX15: 0 | BPZ15: GWS PLASTIC XL | BQA15: 2 | BQB15: 0 | BQD15: GWS PLASTIC XL | BQE15: 2 | BQF15: 0 | BQH15: GWS PLASTIC XL | BQI15: 2 | BQJ15: 0 | BQL15: GWS PLASTIC XL | BQM15: 2 | BQN15: 0 | BQP15: GWS PLASTIC XL | BQQ15: 2 | BQR15: 0 | BQT15: GWS PLASTIC XL | BQU15: 2 | BQV15: 0 | BQX15: GWS PLASTIC XL | BQY15: 2 | BQZ15: 0 | BRB15: GWS PLASTIC XL | BRC15: 2 | BRD15: 0 | BRF15: GWS PLASTIC XL | BRG15: 2 | BRH15: 0 | BRJ15: GWS PLASTIC XL | BRK15: 2 | BRL15: 0 | BRN15: GWS PLASTIC XL | BRO15: 2 | BRP15: 0 | BRR15: GWS PLASTIC XL | BRS15: 2 | BRT15: 0 | BRV15: GWS PLASTIC XL | BRW15: 2 | BRX15: 0 | BRZ15: GWS PLASTIC XL | BSA15: 2 | BSB15: 0 | BSD15: GWS PLASTIC XL | BSE15: 2 | BSF15: 0 | BSH15: GWS PLASTIC XL | BSI15: 2 | BSJ15: 0 | BSL15: GWS PLASTIC XL | BSM15: 2 | BSN15: 0 | BSP15: GWS PLASTIC XL | BSQ15: 2 | BSR15: 0 | BST15: GWS PLASTIC XL | BSU15: 2 | BSV15: 0 | BSX15: GWS PLASTIC XL | BSY15: 2 | BSZ15: 0 | BTB15: GWS PLASTIC XL | BTC15: 2 | BTD15: 0 | BTF15: GWS PLASTIC XL | BTG15: 2 | BTH15: 0 | BTJ15: GWS PLASTIC XL | BTK15: 2 | BTL15: 0 | BTN15: GWS PLASTIC XL | BTO15: 2 | BTP15: 0 | BTR15: GWS PLASTIC XL | BTS15: 2 | BTT15: 0 | BTV15: GWS PLASTIC XL | BTW15: 2 | BTX15: 0 | BTZ15: GWS PLASTIC XL | BUA15: 2 | BUB15: 0 | BUD15: GWS PLASTIC XL | BUE15: 2 | BUF15: 0 | BUH15: GWS PLASTIC XL | BUI15: 2 | BUJ15: 0 | BUL15: GWS PLASTIC XL | BUM15: 2 | BUN15: 0 | BUP15: GWS PLASTIC XL | BUQ15: 2 | BUR15: 0 | BUT15: GWS PLASTIC XL | BUU15: 2 | BUV15: 0 | BUX15: GWS PLASTIC XL | BUY15: 2 | BUZ15: 0 | BVB15: GWS PLASTIC XL | BVC15: 2 | BVD15: 0 | BVF15: GWS PLASTIC XL | BVG15: 2 | BVH15: 0 | BVJ15: GWS PLASTIC XL | BVK15: 2 | BVL15: 0 | BVN15: GWS PLASTIC XL | BVO15: 2 | BVP15: 0 | BVR15: GWS PLASTIC XL | BVS15: 2 | BVT15: 0 | BVV15: GWS PLASTIC XL | BVW15: 2 | BVX15: 0 | BVZ15: GWS PLASTIC XL | BWA15: 2 | BWB15: 0 | BWD15: GWS PLASTIC XL | BWE15: 2 | BWF15: 0 | BWH15: GWS PLASTIC XL | BWI15: 2 | BWJ15: 0 | BWL15: GWS PLASTIC XL | BWM15: 2 | BWN15: 0 | BWP15: GWS PLASTIC XL | BWQ15: 2 | CGB15: 0 | CGD15: GWS PLASTIC XL | CGE15: 2 | CGF15: 0 | CGH15: GWS PLASTIC XL | CGI15: 2 | CGJ15: 0 | CGL15: GWS PLASTIC XL | CGM15: 2 | CGN15: 0 | CGP15: GWS PLASTIC XL | CGQ15: 2 | CGR15: 0 | CGT15: GWS PLASTIC XL | CGU15: 2 | CGV15: 0 | CGX15: GWS PLASTIC XL | CGY15: 2 | CGZ15: 0 | CHB15: GWS PLASTIC XL | CHC15: 2 | CHD15: 0 | CHF15: GWS PLASTIC XL | CHG15: 2 | CHH15: 0 | CHJ15: GWS PLASTIC XL | CHK15: 2 | CHL15: 0 | CHN15: GWS PLASTIC XL | CHO15: 2 | CHP15: 0 | CHR15: GWS PLASTIC XL | CHS15: 2 | CHT15: 0 | CHV15: GWS PLASTIC XL | CHW15: 2 | CHX15: 0 | CHZ15: GWS PLASTIC XL | CIA15: 2 | CIB15: 0 | CID15: GWS PLASTIC XL | CIE15: 2 | CIF15: 0 | CIH15: GWS PLASTIC XL | CII15: 2 | CIJ15: 0 | CIL15: GWS PLASTIC XL | CIM15: 2 | CIN15: 0 | CIP15: GWS PLASTIC XL | CIQ15: 2 | CIR15: 0 | CIT15: GWS PLASTIC XL | CIU15: 2 | CIV15: 0 | CIX15: GWS PLASTIC XL | CIY15: 2 | CIZ15: 0 | CJB15: GWS PLASTIC XL | CJC15: 2 | CJD15: 0 | CJF15: GWS PLASTIC XL | CJG15: 2 | CJH15: 0 | CJJ15: GWS PLASTIC XL | CJK15: 2 | CJL15: 0 | CJN15: GWS PLASTIC XL | CJO15: 2 | CJP15: 0 | CJR15: GWS PLASTIC XL | CJS15: 2 | CJT15: 0 | CJV15: GWS PLASTIC XL | CJW15: 2 | CJX15: 0 | CJZ15: GWS PLASTIC XL | CKA15: 2 | CKB15: 0 | CKD15: GWS PLASTIC XL | CKE15: 2 | CKF15: 0 | CKH15: GWS PLASTIC XL | CKI15: 2 | CKJ15: 0 | CKL15: GWS PLASTIC XL | CKM15: 2 | CKN15: 0 | CKP15: GWS PLASTIC XL | CKQ15: 2 | CKR15: 0 | CKT15: GWS PLASTIC XL | CKU15: 2 | CKV15: 0 | CKX15: GWS PLASTIC XL | CKY15: 2 | CKZ15: 0 | CLB15: GWS PLASTIC XL | CLC15: 2 | CLD15: 0 | CLF15: GWS PLASTIC XL | CLG15: 2 | CLH15: 0 | CLJ15: GWS PLASTIC XL | CLK15: 2 | CLL15: 0 | CLN15: GWS PLASTIC XL | CLO15: 2 | CLP15: 0 | CLR15: GWS PLASTIC XL | CLS15: 2 | CLT15: 0 | CLV15: GWS PLASTIC XL | CLW15: 2 | CLX15: 0 | CLZ15: GWS PLASTIC XL | CMA15: 2 | CMB15: 0 | CMD15: GWS PLASTIC XL | CME15: 2 | CMF15: 0 | CMH15: GWS PLASTIC XL | CMI15: 2 | CMJ15: 0 | CML15: GWS PLASTIC XL | CMM15: 2 | CMN15: 0 | CMP15: GWS PLASTIC XL | CMQ15: 2 | CMR15: 0 | CMT15: GWS PLASTIC XL | CMU15: 2 | CMV15: 0 | CMX15: GWS PLASTIC XL | CMY15: 2 | CMZ15: 0 | CNB15: GWS PLASTIC XL | CNC15: 2 | CND15: 0 | CNF15: GWS PLASTIC XL | CNG15: 2 | CNH15: 0 | CNJ15: GWS PLASTIC XL | CNK15: 2 | CNL15: 0 | CNN15: GWS PLASTIC XL | CNO15: 2 | CNP15: 0 | CNR15: GWS PLASTIC XL | CNS15: 2 | CNT15: 0 | CNV15: GWS PLASTIC XL | CNW15: 2 | CNX15: 0 | CNZ15: GWS PLASTIC XL | COA15: 2 | COB15: 0 | COD15: GWS PLASTIC XL | COE15: 2 | COF15: 0 | COH15: GWS PLASTIC XL | COI15: 2 | COJ15: 0 | COL15: GWS PLASTIC XL | COM15: 2 | CON15: 0 | COP15: GWS PLASTIC XL | COQ15: 2 | COR15: 0 | COT15: GWS PLASTIC XL | COU15: 2 | COV15: 0 | COX15: GWS PLASTIC XL | COY15: 2 | COZ15: 0 | CPB15: GWS PLASTIC XL | CPC15: 2 | CPD15: 0 | CPF15: GWS PLASTIC XL | CPG15: 2 | CPH15: 0 | CPJ15: GWS PLASTIC XL | CPK15: 2 | CPL15: 0 | CPN15: GWS PLASTIC XL | CPO15: 2 | CPP15: 0 | CPR15: GWS PLASTIC XL | CPS15: 2 | CPT15: 0 | CPV15: GWS PLASTIC XL | CPW15: 2 | CPX15: 0 | CPZ15: GWS PLASTIC XL | CQA15: 2 | CQB15: 0 | CQD15: GWS PLASTIC XL | CQE15: 2 | CQF15: 0 | CQH15: GWS PLASTIC XL | CQI15: 2 | CQJ15: 0 | CQL15: GWS PLASTIC XL | CQM15: 2 | CQN15: 0 | CQP15: GWS PLASTIC XL | CQQ15: 2 | CQR15: 0 | CQT15: GWS PLASTIC XL | CQU15: 2 | CQV15: 0 | CQX15: GWS PLASTIC XL | CQY15: 2 | CQZ15: 0 | CRB15: GWS PLASTIC XL | CRC15: 2 | CRD15: 0 | CRF15: GWS PLASTIC XL | CRG15: 2 | CRH15: 0 | CRJ15: GWS PLASTIC XL | CRK15: 2 | CRL15: 0 | CRN15: GWS PLASTIC XL | CRO15: 2 | CRP15: 0 | CRR15: GWS PLASTIC XL | CRS15: 2 | CRT15: 0 | CRV15: GWS PLASTIC XL | CRW15: 2 | CRX15: 0 | CRZ15: GWS PLASTIC XL | CSA15: 2 | CSB15: 0 | CSD15: GWS PLASTIC XL | CSE15: 2 | CSF15: 0 | CSH15: GWS PLASTIC XL | CSI15: 2 | CSJ15: 0 | CSL15: GWS PLASTIC XL | CSM15: 2 | CSN15: 0 | CSP15: GWS PLASTIC XL | CSQ15: 2 | CSR15: 0 | CST15: GWS PLASTIC XL | CSU15: 2 | CSV15: 0 | CSX15: GWS PLASTIC XL | CSY15: 2 | CSZ15: 0 | CTB15: GWS PLASTIC XL | CTC15: 2 | CTD15: 0 | CTF15: GWS PLASTIC XL | CTG15: 2 | CTH15: 0 | CTJ15: GWS PLASTIC XL | CTK15: 2 | CTL15: 0 | CTN15: GWS PLASTIC XL | CTO15: 2 | CTP15: 0 | CTR15: GWS PLASTIC XL | CTS15: 2 | CTT15: 0 | CTV15: GWS PLASTIC XL | CTW15: 2 | CTX15: 0 | CTZ15: GWS PLASTIC XL | CUA15: 2 | CUB15: 0 | CUD15: GWS PLASTIC XL | CUE15: 2 | CUF15: 0 | CUH15: GWS PLASTIC XL | CUI15: 2 | CUJ15: 0 | CUL15: GWS PLASTIC XL | CUM15: 2 | CUN15: 0 | CUP15: GWS PLASTIC XL | CUQ15: 2 | CUR15: 0 | CUT15: GWS PLASTIC XL | CUU15: 2 | CUV15: 0 | CUX15: GWS PLASTIC XL | CUY15: 2 | CUZ15: 0 | CVB15: GWS PLASTIC XL | CVC15: 2 | CVD15: 0 | CVF15: GWS PLASTIC XL | CVG15: 2 | CVH15: 0 | CVJ15: GWS PLASTIC XL | CVK15: 2 | CVL15: 0 | CVN15: GWS PLASTIC XL | CVO15: 2 | CVP15: 0 | CVR15: GWS PLASTIC XL | CVS15: 2 | CVT15: 0 | CVV15: GWS PLASTIC XL | CVW15: 2 | CVX15: 0 | CVZ15: GWS PLASTIC XL | CWA15: 2 | CWB15: 0 | CWD15: GWS PLASTIC XL | CWE15: 2 | CWF15: 0 | CWH15: GWS PLASTIC XL | CWI15: 2 | CWJ15: 0 | CWL15: GWS PLASTIC XL | CWM15: 2 | CWN15: 0 | CWP15: GWS PLASTIC XL | CWQ15: 2 | CWR15: 0 | CWT15: GWS PLASTIC XL | CWU15: 2 | CWV15: 0 | CWX15: GWS PLASTIC XL | CWY15: 2 | CWZ15: 0 | CXB15: GWS PLASTIC XL | CXC15: 2 | CXD15: 0 | CXF15: GWS PLASTIC XL | CXG15: 2 | CXH15: 0 | CXJ15: GWS PLASTIC XL | CXK15: 2 | CXL15: 0 | CXN15: GWS PLASTIC XL | CXO15: 2 | CXP15: 0 | CXR15: GWS PLASTIC XL | CXS15: 2 | CXT15: 0 | CXV15: GWS PLASTIC XL | CXW15: 2 | CXX15: 0 | CXZ15: GWS PLASTIC XL | CYA15: 2 | CYB15: 0 | CYD15: GWS PLASTIC XL | CYE15: 2 | CYF15: 0 | CYH15: GWS PLASTIC XL | CYI15: 2 | CYJ15: 0 | CYL15: GWS PLASTIC XL | CYM15: 2 | CYN15: 0 | CYP15: GWS PLASTIC XL | CYQ15: 2 | CYR15: 0 | CYT15: GWS PLASTIC XL | CYU15: 2 | CYV15: 0 | CYX15: GWS PLASTIC XL | CYY15: 2 | CYZ15: 0 | CZB15: GWS PLASTIC XL | CZC15: 2 | CZD15: 0 | CZF15: GWS PLASTIC XL | CZG15: 2 | CZH15: 0 | CZJ15: GWS PLASTIC XL | CZK15: 2 | CZL15: 0 | CZN15: GWS PLASTIC XL | CZO15: 2 | CZP15: 0 | CZR15: GWS PLASTIC XL | CZS15: 2 | CZT15: 0 | CZV15: GWS PLASTIC XL | CZW15: 2 | CZX15: 0 | CZZ15: GWS PLASTIC XL | DAA15: 2 | DAB15: 0 | DAD15: GWS PLASTIC XL | DAE15: 2 | DAF15: 0 | DAH15: GWS PLASTIC XL | DAI15: 2 | DAJ15: 0 | DAL15: GWS PLASTIC XL | DAM15: 2 | DAN15: 0 | DAP15: GWS PLASTIC XL | DAQ15: 2 | DAR15: 0 | DAT15: GWS PLASTIC XL | DAU15: 2 | DAV15: 0 | DAX15: GWS PLASTIC XL | DAY15: 2 | DAZ15: 0 | DBB15: GWS PLASTIC XL | DBC15: 2 | DBD15: 0 | DBF15: GWS PLASTIC XL | DBG15: 2 | DBH15: 0 | DBJ15: GWS PLASTIC XL | DBK15: 2 | DBL15: 0 | DBN15: GWS PLASTIC XL | DBO15: 2 | DBP15: 0 | DBR15: GWS PLASTIC XL | DBS15: 2 | DBT15: 0 | DBV15: GWS PLASTIC XL | DBW15: 2 | DBX15: 0 | DBZ15: GWS PLASTIC XL | DCA15: 2 | DCB15: 0 | DCD15: GWS PLASTIC XL | DCE15: 2 | DCF15: 0 | DCH15: GWS PLASTIC XL | DCI15: 2 | DCJ15: 0
B16: Promatrix Shaker | C16: 1 | D16: 200 | F16: 200
B17: Plastic L | C17: 1 | D17: 0 | F17: 0
A53: TOTAL | C53: =SUM(C6:C52) -> 12 | D53: =SUM(D6:D52) -> 10325 | E53: =SUM(E6:E52) -> 137 | F53: =SUM(F6:F52) -> 10325

Sheet PRODUCT LIST
A1: INVENTORY ITEMS
A3: (Note: Don't rename after encoding & posting)
A4: PRODUCT NAME
A5: Prothin Lipothin 60 Caps.
A6: Prothin Multivitamins 30 Gummies
A7: Prothin Pre-Game 30 Sachets
A8: Prothin Brew
A9: Prothin Creatine 60s
A10: Prothin Isolate 10s
A11: Prothin Isolate 60s
A12: Prothin Mass Gainer 27s
A13: Prothin Mass Gainer 54s
... A1192: Goliath Labs Whey Protein 100% 5lbs

Sheet NO SALE-FRONT
A1: BRANCH : | H1: RIDER DELIVERY SUMMARY
A2: DATE : | E2: SYSTEM DATE: | H2: RIDER NAME (1-4) | I2: PRODUCT AMOUNT | J2: DEL FEE | K2: SUBTOTAL | L2: INCENTIVES | M2: TOTAL | N2: REMARKS
H3: JAIME | I3: 0 | M3: 0
A4: SALES Breakdown (CASH) | E4: Number of products | H4: NAME | I4: 0 | M4: 0
B5: Walk in | C5: 0 | E5: Walk-in: | F5: 0 | I5: 0 | M5: 0
B6: Delivery | C6: 0 | E6: Delivery: | F6: 0 | I6: 0 | M6: 0
B7: Franchise | C7: 0 | E7: Franchise: | F7: 0 | I7: 0
B8: Prothin Dealer | C8: 0 | E8: Prothin Dealers: | F8: 0 | I8: 0
B9: Agent (Cash) | C9: 0 | E9: Shipping: | F9: 0 | H9: Total: | I9: 0 | J9: 0 | K9: 0 | L9: 0 | M9: 0
B10: Delivery Fee | C10: 0 | E10: Apparels: | F10: 0
B11: SUBTOTAL | E11: Equipment: | F11: 0 | H11: MONEY BREAKDOWN | J11: Quantity | L11: EXPENSES
E12: Agent: | F12: 0 | H12: 1000 | I12: X | K12: 0 | L12: NAME | M12: PARTICULAR/S | N12: AMOUNT
B13: Credit Card (Walk In) | C13: 0 | H13: 500 | I13: X | K13: 0 | L13: Rent
B14: Credit Card (Delivery) | C14: 0 | H14: 200 | I14: X | K14: 0 | L14: Meralco
B15: Credit Card (Agent) | C15: 0 | H15: 100 | I15: X | K15: 0 | L15: Internet (Globe or Royal cab)
B16: Walk in (Online) | C16: 0 | E16: Delivery Fee (Online) | F16: 0 | H16: 50 | I16: X | K16: 0 | L16: Water Bills
B17: Walk in (Online) - Franchise | C17: 0 | E17: Delivery Fee (Credit Card) | F17: 0 | H17: 20 | I17: X | K17: 0 | L17: INCENTIVES ETC.
B18: Walk in (Online) - Prothin Dealer | C18: 0 | E18: Franchise (Online) | F18: 0 | H18: 10 | I18: X | K18: 0 | L18: Load for Store CP
B19: Walk in (Online) - Agent | C19: 0 | E19: Prothin Dealer (Online) | F19: 0 | H19: 5 | I19: X | K19: 0 | L19: ABONO LALAMOVE
B20: Delivery (Online) | C20: 0 | E20: Shipping Fee | F20: 0 | H20: 1 | I20: X | K20: 0
B21: Delivery (Online) - Franchise | C21: 0 | E21: Agent (Online) | F21: 0
B22: Delivery (Online) Prothin Dealer | C22: 0 | E22: TOTAL
B23: Delivery (Online) Agent | C23: 0 | H23: check payment
B24: Shipping (LBC/LALAMOVE) | C24: 0 | H24: TOTAL | K24: 0 | N24: 0
B25: Shipping - Franchise | C25: 0
B26: Shipping - Prothin Dealer | C26: 0
B27: Shipping - Agent | C27: 0
B28: Shipping (Shopee/Lazada) | C28: 0 | L28: OTHERS:
B29: TOTAL ONLINE, CC & SHIPPING | H29: RIDER/DRIVER EXPENSE
H30: NAME : | I30: PARTICULAR/S | J30: AMOUNT
B31: TOTAL WALK IN : | D31: 0
B32: (CASH,CC, AND ONLINE) | D32: 0
B33: TOTAL DELIVERY : | D33: 0
B34: (CASH,CC, AND ONLINE)
B35: TOTAL SHIPPING : | D35: 0
B36: (CASH,CC, AND ONLINE)
B37: TOTAL FRANCHISE : | D37: 0 | L37: TOTAL OTHER EXP: | N37: 0
B38: (CASH AND ONLINE)
B39: TOTAL PROTHIN DEALER : | D39: 0
B40: (CASH AND ONLINE)
B41: TOTAL AGENT : | D41: 0
B42: (CASH,ONLINE AND CC) | H42: TOTAL RIDER/DRIVER EXPENSE | J42: 0
A43: EXPENSES | E43: NOTES: | F43: FREEBIES
B44: Riders/Drivers (Incentive) | C44: ………………... | D44: 0 | H44: SHIPPING EXPENSE | J44: ORDERS | K44: MARKETING
B45: Riders/Drivers (Expense) | C45: ………………... | D45: 0 | H45: NAME | I45: PARTICULAR/S | J45: AMOUNT | K45: AMOUNT
B46: Shipping Expense (TOTAL) | C46: ………………... | D46: 0
B47: MAJOR EXPENSES | C47: ………………... | D47: 0
B48: OTHER EXPENSES | C48: ………………... | D48: 0
B49: TOTAL | C49: ………………... | D49: 0
A51: SUMMARY (for bank deposit)
B52: CASH | C52: 0
A53: less | B53: EXPENSES | C53: 0
B54: TOTAL | C54: 0
A56: TOTAL CASH DEPOSIT: | C56: 0 | D56: 0 | H56: TOTAL RIDER/DRIVER EXPENSE | J56: 0 | K56: 0
A57: OVERALL SALES: | C57: 0
A58: TOTAL PRODUCTS (WALK IN) | C58: 0
A59: TOTAL PRODUCTS (DELIVERY) | C59: 0
A60: TOTAL PRODUCTS (SHIPPING) | C60: 0
A61: TOTAL APPARELS: | C61: 0
A62: TOTAL EQUIPMENT: | C62: 0 | E62: PREPARED BY :
A63: TOTAL FRANCHISE | C63: 0
A64: TOTAL PROTHIN DEALER | C64: 0 | E64: Name and Signature/Date
A65: TOTAL AGENT | C65: 0
